Workbook

Sheet README
A1: Калькулятор Adaptive Lock EV (демо)
A2: Назначение: расчет следующего допустимого шага системы.
A3: Важно: калькулятор не торгует, только рассчитывает.
A4: Логика следующего шага рассчитывается на листах Calculations/Scenario_Up/Scenario_Down/Recommendations.

Sheet Broker_Params
A1: Параметр | B1: Значение | C1: Комментарий
A2: Баланс счёта | B2: 10000 | C2: Демо
A3: Эквити | B3: 10000 | C3: Демо
A4: Плечо | B4: 100 | C4: 1:100
A5: Спред (пункты) | B5: 2 | C5: Демо
A6: Комиссия за 1 лот | B6: 0.5 | C6: Демо
A7: Проскальзывание (пункты) | B7: 1 | C7: Демо
A8: Своп BUY | B8: 0 | C8: Демо
A9: Своп SELL | B9: 0 | C9: Демо
A10: Маржа на 1 лот | B10: 1000 | C10: Демо
A11: Мин. лот | B11: 0.01 | C11: Демо
A12: Шаг лота | B12: 0.01 | C12: Демо
A13: Макс. лот | B13: 100 | C13: Демо

Sheet Symbol_Params
A1: Параметр | B1: Значение | C1: Комментарий
A2: Символ | B2: EURUSD | C2: Демо
A3: Digits | B3: 5 | C3: Точность
A4: Point | B4: 0.0001 | C4: Шаг цены
A5: Tick Size | B5: 0.0001 | C5: Размер тика
A6: Tick Value | B6: 1 | C6: Стоимость тика
A7: Pip Value 1 Lot | B7: 10 | C7: Стоимость пункта
A8: Contract Size | B8: 100000 | C8: Контракт
A9: ATR Period Short | B9: 14 | C9: Демо
A10: ATR Period Long | B10: 100 | C10: Демо
A11: EMA Period | B11: 50 | C11: Демо

Sheet System_Params
A1: Параметр | B1: Значение
A2: Base Lock Buy Lot | B2: 0.1
A3: Base Lock Sell Lot | B3: 0.1
A4: Q Min | B4: 0.01
A5: Q Max | B5: 0.02
A6: Max Total Lot | B6: 0.3
A7: Max Exposure | B7: 0.05
A8: Z Entry Level | B8: 1.5
A9: V Mean Revert Max | B9: 1.2
A10: V Volatile Stop | B10: 1.5
A11: DD Stress Level | B11: 0.07
A12: DD Escape Level | B12: 0.15
A13: DD Beta Protection | B13: 0.1
... A17: Expected Mu | B17: 6

Sheet Current_Positions
A1: ID | B1: Тип | C1: Лот | D1: Цена открытия | E1: Плавающий PnL | F1: Комментарий | G1: Убыток (USD) | H1: Убыток (пункты) | J1: Сумма BUY | K1: =SUMIFS(C2:C100,B2:B100,"BUY")
A2: 1 | B2: BUY | C2: 0.01 | D2: 1.17385 | E2: =(Market_Data!B2-D2)/Symbol_Params!B4*C2*Symbol_Params!B7 | F2: минусовой замок | G2: -144.06 | J2: Сумма SELL | K2: =SUMIFS(C2:C100,B2:B100,"SELL")
A3: 2 | B3: SELL | C3: 0.01 | D3: 1.17175 | E3: =(D3-Market_Data!B2)/Symbol_Params!B4*C3*Symbol_Params!B7 | F3: противоположная нога

Sheet Market_Data
A1: Параметр | B1: Значение
A2: Текущая цена | B2: 1.17193
A3: EMA | B3: 1.1726
A4: ATR Short | B4: 0.0018
A5: ATR Long | B5: 0.0024
A6: Текущий DD | B6: 0.02
A7: Последний PnL 10 циклов | B7: 5

Sheet Calculations
A1: Z | B1: =(Market_Data!B2-Market_Data!B3)/Market_Data!B4
A2: V | B2: =Market_Data!B4/Market_Data!B5
A3: Regime | B3: =IF(B2>System_Params!B10,"VOLATILE",IF(B2<System_Params!B9,"MEAN_REVERT","NEUTRAL"))
A4: Confidence | B4: =MIN(ABS(B1)/2,1)
A5: Q | B5: =MIN(MAX(System_Params!B4+System_Params!B4*B4,System_Params!B4),System_Params!B5)
A6: Q adj | B6: =IF(B3="NEUTRAL",B5*0.5,IF(B3="VOLATILE",0,B5))
A7: Beta | B7: =IF(Market_Data!B6>System_Params!B13,System_Params!B14,0.7-0.4*B4)
A8: Cost | B8: =(Broker_Params!B5*B6*Symbol_Params!B7)+(Broker_Params!B6*B6)+(Broker_Params!B7*B6*Symbol_Params!B7)
A9: EV | B9: =(System_Params!B17*B6*Symbol_Params!B7)-B8
A10: MinMovePoints | B10: =(B8*System_Params!B16)/(B6*Symbol_Params!B7)
A11: MinMovePrice | B11: =B10*Symbol_Params!B4
A12: TotalLot | B12: =Current_Positions!K1+Current_Positions!K2
A13: Exposure | B13: =ABS(Current_Positions!K1-Current_Positions!K2)
A14: RiskOK | B14: =IF(AND(B12<=System_Params!B6,B13<=System_Params!B7),"YES","NO")
A15: EV_OK | B15: =IF(B9>System_Params!B15,"ALLOW","BLOCK")

Sheet Recommendations
A1: Direction | B1: Action | C1: Type | D1: Price | E1: Lot | F1: Comment
A2: UP | B2: =Scenario_Up!B2 | C2: =Scenario_Up!B3 | D2: =Scenario_Up!B1 | E2: =Scenario_Up!B4 | F2: =Scenario_Up!B5
A3: DOWN | B3: =Scenario_Down!B2 | C3: =Scenario_Down!B3 | D3: =Scenario_Down!B1 | E3: =Scenario_Down!B4 | F3: =Scenario_Down!B5

Sheet Scenario_Up
A1: TriggerUp | B1: =Market_Data!B2+Calculations!B11
A2: Action | B2: =IF(AND(Calculations!B1>System_Params!B8,Calculations!B3="MEAN_REVERT",Calculations!B14="YES",Calculations!B15="ALLOW"),"OPEN","NO_ACTION")
A3: Type | B3: =IF(B2="OPEN","SELL","")
A4: Lot | B4: =IF(B2="OPEN",Calculations!B6,0)
A5: Comment | B5: =IF(B2="OPEN","Mean reversion SELL","Блокировка условий")

Sheet Scenario_Down
A1: TriggerDown | B1: =Market_Data!B2-Calculations!B11
A2: Action | B2: =IF(AND(Calculations!B1<-System_Params!B8,Calculations!B3="MEAN_REVERT",Calculations!B14="YES",Calculations!B15="ALLOW"),"OPEN","NO_ACTION")
A3: Type | B3: =IF(B2="OPEN","BUY","")
A4: Lot | B4: =IF(B2="OPEN",Calculations!B6,0)
A5: Comment | B5: =IF(B2="OPEN","Mean reversion BUY","Блокировка условий")

Sheet Risk_Control
A1: Демо-данные заполнены

Sheet Trade_Log
A1: Демо-данные заполнены

Sheet Change_Log
A1: Демо-данные заполнены
