Workbook

Sheet Ввод
A1: Калькулятор Adaptive EV
A3: Брокер | B3: DemoBroker
A4: Символ | B4: EURUSD
A5: Знаков после запятой | B5: 5
A6: Размер контракта | B6: 100000
A7: Кредитное плечо | B7: 100
A8: Валюта счета | B8: USD
A9: Баланс | B9: 100000
A10: Эквити | B10: 99998.7
A11: Свободная маржа | B11: 99875.5
A12: Текущая цена (mid) | B12: 1.23184
A13: Bid | B13: =B12-B15/2
A14: Ask | B14: =B12+B15/2
A15: Спред (цена) | B15: 8e-05
A16: ATR | B16: 0.0008
A17: Alpha (α) | B17: 0.3
A18: Шаг Δ | B18: 0.00028
A19: Gamma (γ) | B19: 0.08
A20: Минимум SELL Ls,min | B20: 0.25
A21: Предел просадки Dmax, % | B21: 2
A22: Лимит нагрузки маржи, % | B22: 60
A23: Коэффициент режима (0.5..2.0) | B23: 1
A25: Уровень маржи, % | B25: =IF(Расчеты!B13=0,0,B10/Расчеты!B13*100)
A26: Статус риска | B26: =IF(OR(Расчеты!B9="FAIL",Расчеты!B14>B22,Расчеты!B16<-B21),"СТРЕСС/СОКРАЩЕНИЕ","НОРМА")

Sheet Позиции
A1: ID | B1: Активна (Y/N) | C1: Направление (BUY/SELL) | D1: Лот | E1: Цена открытия | F1: SL | G1: TP | H1: Комиссия | I1: Своп | J1: Текущая цена | K1: Разница цены | L1: P/L, USD | M1: Маржа, USD | N1: Лот частичного закрытия | O1: Действие | P1: Расчет ΔL_s/ΔL_b | Q1: Ключ актив+направление
A2: 1 | B2: Y | C2: SELL | D2: 0.1 | E2: 1.23125 | F2: 0 | G2: 0 | H2: 0 | I2: 0 | J2: =IF(C2="BUY",Ввод!B13,Ввод!B14) | K2: =IF(C2="BUY",J2-E2,E2-J2) | L2: =IF(B2="Y",K2*D2*Ввод!B6+H2+I2,0) | M2: =IF(B2="Y",D2*Ввод!B6*J2/Ввод!B7,0) | N2: =IF(B2="Y",ROUND(MIN(D2*Ввод!B19,D2*0.5),2),0) | O2: =IF(B2<>"Y","НЕТ",IF(AND(Расчеты!B11="ДА",ABS(K2)>=Ввод!B18),"ЧАСТИЧНО ЗАКРЫТЬ","ДЕРЖАТЬ")) | P2: =IF(B2<>"Y",0,IFERROR((Ввод!B12-Расчеты!B3-Ввод!B15/2+Расчеты!B6)/(Расчеты!B4-Ввод!B12-Ввод!B15/2-Расчеты!B6),0)) | Q2: =IF(B2="Y",B2&C2,"")
A3: 2 | B3: Y | C3: BUY | D3: 0.1 | E3: 1.23267 | F3: 0 | G3: 0 | H3: 0 | I3: 0 | J3: =IF(C3="BUY",Ввод!B13,Ввод!B14) | K3: =IF(C3="BUY",J3-E3,E3-J3) | L3: =IF(B3="Y",K3*D3*Ввод!B6+H3+I3,0) | M3: =IF(B3="Y",D3*Ввод!B6*J3/Ввод!B7,0) | N3: =IF(B3="Y",ROUND(MIN(D3*Ввод!B19,D3*0.5),2),0) | O3: =IF(B3<>"Y","НЕТ",IF(AND(Расчеты!B11="ДА",ABS(K3)>=Ввод!B18),"ЧАСТИЧНО ЗАКРЫТЬ","ДЕРЖАТЬ")) | P3: =IF(B3<>"Y",0,IFERROR((Ввод!B12-Расчеты!B3-Ввод!B15/2+Расчеты!B6)/(Расчеты!B4-Ввод!B12-Ввод!B15/2-Расчеты!B6),0)) | Q3: =IF(B3="Y",B3&C3,"")
J4: =IF(C4="BUY",Ввод!B13,Ввод!B14) | K4: =IF(C4="BUY",J4-E4,E4-J4) | L4: =IF(B4="Y",K4*D4*Ввод!B6+H4+I4,0) | M4: =IF(B4="Y",D4*Ввод!B6*J4/Ввод!B7,0) | N4: =IF(B4="Y",ROUND(MIN(D4*Ввод!B19,D4*0.5),2),0) | O4: =IF(B4<>"Y","НЕТ",IF(AND(Расчеты!B11="ДА",ABS(K4)>=Ввод!B18),"ЧАСТИЧНО ЗАКРЫТЬ","ДЕРЖАТЬ")) | P4: =IF(B4<>"Y",0,IFERROR((Ввод!B12-Расчеты!B3-Ввод!B15/2+Расчеты!B6)/(Расчеты!B4-Ввод!B12-Ввод!B15/2-Расчеты!B6),0)) | Q4: =IF(B4="Y",B4&C4,"")
J5: =IF(C5="BUY",Ввод!B13,Ввод!B14) | K5: =IF(C5="BUY",J5-E5,E5-J5) | L5: =IF(B5="Y",K5*D5*Ввод!B6+H5+I5,0) | M5: =IF(B5="Y",D5*Ввод!B6*J5/Ввод!B7,0) | N5: =IF(B5="Y",ROUND(MIN(D5*Ввод!B19,D5*0.5),2),0) | O5: =IF(B5<>"Y","НЕТ",IF(AND(Расчеты!B11="ДА",ABS(K5)>=Ввод!B18),"ЧАСТИЧНО ЗАКРЫТЬ","ДЕРЖАТЬ")) | P5: =IF(B5<>"Y",0,IFERROR((Ввод!B12-Расчеты!B3-Ввод!B15/2+Расчеты!B6)/(Расчеты!B4-Ввод!B12-Ввод!B15/2-Расчеты!B6),0)) | Q5: =IF(B5="Y",B5&C5,"")
J6: =IF(C6="BUY",Ввод!B13,Ввод!B14) | K6: =IF(C6="BUY",J6-E6,E6-J6) | L6: =IF(B6="Y",K6*D6*Ввод!B6+H6+I6,0) | M6: =IF(B6="Y",D6*Ввод!B6*J6/Ввод!B7,0) | N6: =IF(B6="Y",ROUND(MIN(D6*Ввод!B19,D6*0.5),2),0) | O6: =IF(B6<>"Y","НЕТ",IF(AND(Расчеты!B11="ДА",ABS(K6)>=Ввод!B18),"ЧАСТИЧНО ЗАКРЫТЬ","ДЕРЖАТЬ")) | P6: =IF(B6<>"Y",0,IFERROR((Ввод!B12-Расчеты!B3-Ввод!B15/2+Расчеты!B6)/(Расчеты!B4-Ввод!B12-Ввод!B15/2-Расчеты!B6),0)) | Q6: =IF(B6="Y",B6&C6,"")
J7: =IF(C7="BUY",Ввод!B13,Ввод!B14) | K7: =IF(C7="BUY",J7-E7,E7-J7) | L7: =IF(B7="Y",K7*D7*Ввод!B6+H7+I7,0) | M7: =IF(B7="Y",D7*Ввод!B6*J7/Ввод!B7,0) | N7: =IF(B7="Y",ROUND(MIN(D7*Ввод!B19,D7*0.5),2),0) | O7: =IF(B7<>"Y","НЕТ",IF(AND(Расчеты!B11="ДА",ABS(K7)>=Ввод!B18),"ЧАСТИЧНО ЗАКРЫТЬ","ДЕРЖАТЬ")) | P7: =IF(B7<>"Y",0,IFERROR((Ввод!B12-Расчеты!B3-Ввод!B15/2+Расчеты!B6)/(Расчеты!B4-Ввод!B12-Ввод!B15/2-Расчеты!B6),0)) | Q7: =IF(B7="Y",B7&C7,"")
J8: =IF(C8="BUY",Ввод!B13,Ввод!B14) | K8: =IF(C8="BUY",J8-E8,E8-J8) | L8: =IF(B8="Y",K8*D8*Ввод!B6+H8+I8,0) | M8: =IF(B8="Y",D8*Ввод!B6*J8/Ввод!B7,0) | N8: =IF(B8="Y",ROUND(MIN(D8*Ввод!B19,D8*0.5),2),0) | O8: =IF(B8<>"Y","НЕТ",IF(AND(Расчеты!B11="ДА",ABS(K8)>=Ввод!B18),"ЧАСТИЧНО ЗАКРЫТЬ","ДЕРЖАТЬ")) | P8: =IF(B8<>"Y",0,IFERROR((Ввод!B12-Расчеты!B3-Ввод!B15/2+Расчеты!B6)/(Расчеты!B4-Ввод!B12-Ввод!B15/2-Расчеты!B6),0)) | Q8: =IF(B8="Y",B8&C8,"")
J9: =IF(C9="BUY",Ввод!B13,Ввод!B14) | K9: =IF(C9="BUY",J9-E9,E9-J9) | L9: =IF(B9="Y",K9*D9*Ввод!B6+H9+I9,0) | M9: =IF(B9="Y",D9*Ввод!B6*J9/Ввод!B7,0) | N9: =IF(B9="Y",ROUND(MIN(D9*Ввод!B19,D9*0.5),2),0) | O9: =IF(B9<>"Y","НЕТ",IF(AND(Расчеты!B11="ДА",ABS(K9)>=Ввод!B18),"ЧАСТИЧНО ЗАКРЫТЬ","ДЕРЖАТЬ")) | P9: =IF(B9<>"Y",0,IFERROR((Ввод!B12-Расчеты!B3-Ввод!B15/2+Расчеты!B6)/(Расчеты!B4-Ввод!B12-Ввод!B15/2-Расчеты!B6),0)) | Q9: =IF(B9="Y",B9&C9,"")
J10: =IF(C10="BUY",Ввод!B13,Ввод!B14) | K10: =IF(C10="BUY",J10-E10,E10-J10) | L10: =IF(B10="Y",K10*D10*Ввод!B6+H10+I10,0) | M10: =IF(B10="Y",D10*Ввод!B6*J10/Ввод!B7,0) | N10: =IF(B10="Y",ROUND(MIN(D10*Ввод!B19,D10*0.5),2),0) | O10: =IF(B10<>"Y","НЕТ",IF(AND(Расчеты!B11="ДА",ABS(K10)>=Ввод!B18),"ЧАСТИЧНО ЗАКРЫТЬ","ДЕРЖАТЬ")) | P10: =IF(B10<>"Y",0,IFERROR((Ввод!B12-Расчеты!B3-Ввод!B15/2+Расчеты!B6)/(Расчеты!B4-Ввод!B12-Ввод!B15/2-Расчеты!B6),0)) | Q10: =IF(B10="Y",B10&C10,"")
J11: =IF(C11="BUY",Ввод!B13,Ввод!B14) | K11: =IF(C11="BUY",J11-E11,E11-J11) | L11: =IF(B11="Y",K11*D11*Ввод!B6+H11+I11,0) | M11: =IF(B11="Y",D11*Ввод!B6*J11/Ввод!B7,0) | N11: =IF(B11="Y",ROUND(MIN(D11*Ввод!B19,D11*0.5),2),0) | O11: =IF(B11<>"Y","НЕТ",IF(AND(Расчеты!B11="ДА",ABS(K11)>=Ввод!B18),"ЧАСТИЧНО ЗАКРЫТЬ","ДЕРЖАТЬ")) | P11: =IF(B11<>"Y",0,IFERROR((Ввод!B12-Расчеты!B3-Ввод!B15/2+Расчеты!B6)/(Расчеты!B4-Ввод!B12-Ввод!B15/2-Расчеты!B6),0)) | Q11: =IF(B11="Y",B11&C11,"")
J12: =IF(C12="BUY",Ввод!B13,Ввод!B14) | K12: =IF(C12="BUY",J12-E12,E12-J12) | L12: =IF(B12="Y",K12*D12*Ввод!B6+H12+I12,0) | M12: =IF(B12="Y",D12*Ввод!B6*J12/Ввод!B7,0) | N12: =IF(B12="Y",ROUND(MIN(D12*Ввод!B19,D12*0.5),2),0) | O12: =IF(B12<>"Y","НЕТ",IF(AND(Расчеты!B11="ДА",ABS(K12)>=Ввод!B18),"ЧАСТИЧНО ЗАКРЫТЬ","ДЕРЖАТЬ")) | P12: =IF(B12<>"Y",0,IFERROR((Ввод!B12-Расчеты!B3-Ввод!B15/2+Расчеты!B6)/(Расчеты!B4-Ввод!B12-Ввод!B15/2-Расчеты!B6),0)) | Q12: =IF(B12="Y",B12&C12,"")
J13: =IF(C13="BUY",Ввод!B13,Ввод!B14) | K13: =IF(C13="BUY",J13-E13,E13-J13) | L13: =IF(B13="Y",K13*D13*Ввод!B6+H13+I13,0) | M13: =IF(B13="Y",D13*Ввод!B6*J13/Ввод!B7,0) | N13: =IF(B13="Y",ROUND(MIN(D13*Ввод!B19,D13*0.5),2),0) | O13: =IF(B13<>"Y","НЕТ",IF(AND(Расчеты!B11="ДА",ABS(K13)>=Ввод!B18),"ЧАСТИЧНО ЗАКРЫТЬ","ДЕРЖАТЬ")) | P13: =IF(B13<>"Y",0,IFERROR((Ввод!B12-Расчеты!B3-Ввод!B15/2+Расчеты!B6)/(Расчеты!B4-Ввод!B12-Ввод!B15/2-Расчеты!B6),0)) | Q13: =IF(B13="Y",B13&C13,"")
J14: =IF(C14="BUY",Ввод!B13,Ввод!B14) | K14: =IF(C14="BUY",J14-E14,E14-J14) | L14: =IF(B14="Y",K14*D14*Ввод!B6+H14+I14,0) | M14: =IF(B14="Y",D14*Ввод!B6*J14/Ввод!B7,0) | N14: =IF(B14="Y",ROUND(MIN(D14*Ввод!B19,D14*0.5),2),0) | O14: =IF(B14<>"Y","НЕТ",IF(AND(Расчеты!B11="ДА",ABS(K14)>=Ввод!B18),"ЧАСТИЧНО ЗАКРЫТЬ","ДЕРЖАТЬ")) | P14: =IF(B14<>"Y",0,IFERROR((Ввод!B12-Расчеты!B3-Ввод!B15/2+Расчеты!B6)/(Расчеты!B4-Ввод!B12-Ввод!B15/2-Расчеты!B6),0)) | Q14: =IF(B14="Y",B14&C14,"")
J15: =IF(C15="BUY",Ввод!B13,Ввод!B14) | K15: =IF(C15="BUY",J15-E15,E15-J15) | L15: =IF(B15="Y",K15*D15*Ввод!B6+H15+I15,0) | M15: =IF(B15="Y",D15*Ввод!B6*J15/Ввод!B7,0) | N15: =IF(B15="Y",ROUND(MIN(D15*Ввод!B19,D15*0.5),2),0) | O15: =IF(B15<>"Y","НЕТ",IF(AND(Расчеты!B11="ДА",ABS(K15)>=Ввод!B18),"ЧАСТИЧНО ЗАКРЫТЬ","ДЕРЖАТЬ")) | P15: =IF(B15<>"Y",0,IFERROR((Ввод!B12-Расчеты!B3-Ввод!B15/2+Расчеты!B6)/(Расчеты!B4-Ввод!B12-Ввод!B15/2-Расчеты!B6),0)) | Q15: =IF(B15="Y",B15&C15,"")
J16: =IF(C16="BUY",Ввод!B13,Ввод!B14) | K16: =IF(C16="BUY",J16-E16,E16-J16) | L16: =IF(B16="Y",K16*D16*Ввод!B6+H16+I16,0) | M16: =IF(B16="Y",D16*Ввод!B6*J16/Ввод!B7,0) | N16: =IF(B16="Y",ROUND(MIN(D16*Ввод!B19,D16*0.5),2),0) | O16: =IF(B16<>"Y","НЕТ",IF(AND(Расчеты!B11="ДА",ABS(K16)>=Ввод!B18),"ЧАСТИЧНО ЗАКРЫТЬ","ДЕРЖАТЬ")) | P16: =IF(B16<>"Y",0,IFERROR((Ввод!B12-Расчеты!B3-Ввод!B15/2+Расчеты!B6)/(Расчеты!B4-Ввод!B12-Ввод!B15/2-Расчеты!B6),0)) | Q16: =IF(B16="Y",B16&C16,"")
J17: =IF(C17="BUY",Ввод!B13,Ввод!B14) | K17: =IF(C17="BUY",J17-E17,E17-J17) | L17: =IF(B17="Y",K17*D17*Ввод!B6+H17+I17,0) | M17: =IF(B17="Y",D17*Ввод!B6*J17/Ввод!B7,0) | N17: =IF(B17="Y",ROUND(MIN(D17*Ввод!B19,D17*0.5),2),0) | O17: =IF(B17<>"Y","НЕТ",IF(AND(Расчеты!B11="ДА",ABS(K17)>=Ввод!B18),"ЧАСТИЧНО ЗАКРЫТЬ","ДЕРЖАТЬ")) | P17: =IF(B17<>"Y",0,IFERROR((Ввод!B12-Расчеты!B3-Ввод!B15/2+Расчеты!B6)/(Расчеты!B4-Ввод!B12-Ввод!B15/2-Расчеты!B6),0)) | Q17: =IF(B17="Y",B17&C17,"")
J18: =IF(C18="BUY",Ввод!B13,Ввод!B14) | K18: =IF(C18="BUY",J18-E18,E18-J18) | L18: =IF(B18="Y",K18*D18*Ввод!B6+H18+I18,0) | M18: =IF(B18="Y",D18*Ввод!B6*J18/Ввод!B7,0) | N18: =IF(B18="Y",ROUND(MIN(D18*Ввод!B19,D18*0.5),2),0) | O18: =IF(B18<>"Y","НЕТ",IF(AND(Расчеты!B11="ДА",ABS(K18)>=Ввод!B18),"ЧАСТИЧНО ЗАКРЫТЬ","ДЕРЖАТЬ")) | P18: =IF(B18<>"Y",0,IFERROR((Ввод!B12-Расчеты!B3-Ввод!B15/2+Расчеты!B6)/(Расчеты!B4-Ввод!B12-Ввод!B15/2-Расчеты!B6),0)) | Q18: =IF(B18="Y",B18&C18,"")
J19: =IF(C19="BUY",Ввод!B13,Ввод!B14) | K19: =IF(C19="BUY",J19-E19,E19-J19) | L19: =IF(B19="Y",K19*D19*Ввод!B6+H19+I19,0) | M19: =IF(B19="Y",D19*Ввод!B6*J19/Ввод!B7,0) | N19: =IF(B19="Y",ROUND(MIN(D19*Ввод!B19,D19*0.5),2),0) | O19: =IF(B19<>"Y","НЕТ",IF(AND(Расчеты!B11="ДА",ABS(K19)>=Ввод!B18),"ЧАСТИЧНО ЗАКРЫТЬ","ДЕРЖАТЬ")) | P19: =IF(B19<>"Y",0,IFERROR((Ввод!B12-Расчеты!B3-Ввод!B15/2+Расчеты!B6)/(Расчеты!B4-Ввод!B12-Ввод!B15/2-Расчеты!B6),0)) | Q19: =IF(B19="Y",B19&C19,"")
J20: =IF(C20="BUY",Ввод!B13,Ввод!B14) | K20: =IF(C20="BUY",J20-E20,E20-J20) | L20: =IF(B20="Y",K20*D20*Ввод!B6+H20+I20,0) | M20: =IF(B20="Y",D20*Ввод!B6*J20/Ввод!B7,0) | N20: =IF(B20="Y",ROUND(MIN(D20*Ввод!B19,D20*0.5),2),0) | O20: =IF(B20<>"Y","НЕТ",IF(AND(Расчеты!B11="ДА",ABS(K20)>=Ввод!B18),"ЧАСТИЧНО ЗАКРЫТЬ","ДЕРЖАТЬ")) | P20: =IF(B20<>"Y",0,IFERROR((Ввод!B12-Расчеты!B3-Ввод!B15/2+Расчеты!B6)/(Расчеты!B4-Ввод!B12-Ввод!B15/2-Расчеты!B6),0)) | Q20: =IF(B20="Y",B20&C20,"")
J21: =IF(C21="BUY",Ввод!B13,Ввод!B14) | K21: =IF(C21="BUY",J21-E21,E21-J21) | L21: =IF(B21="Y",K21*D21*Ввод!B6+H21+I21,0) | M21: =IF(B21="Y",D21*Ввод!B6*J21/Ввод!B7,0) | N21: =IF(B21="Y",ROUND(MIN(D21*Ввод!B19,D21*0.5),2),0) | O21: =IF(B21<>"Y","НЕТ",IF(AND(Расчеты!B11="ДА",ABS(K21)>=Ввод!B18),"ЧАСТИЧНО ЗАКРЫТЬ","ДЕРЖАТЬ")) | P21: =IF(B21<>"Y",0,IFERROR((Ввод!B12-Расчеты!B3-Ввод!B15/2+Расчеты!B6)/(Расчеты!B4-Ввод!B12-Ввод!B15/2-Расчеты!B6),0)) | Q21: =IF(B21="Y",B21&C21,"")
J22: =IF(C22="BUY",Ввод!B13,Ввод!B14) | K22: =IF(C22="BUY",J22-E22,E22-J22) | L22: =IF(B22="Y",K22*D22*Ввод!B6+H22+I22,0) | M22: =IF(B22="Y",D22*Ввод!B6*J22/Ввод!B7,0) | N22: =IF(B22="Y",ROUND(MIN(D22*Ввод!B19,D22*0.5),2),0) | O22: =IF(B22<>"Y","НЕТ",IF(AND(Расчеты!B11="ДА",ABS(K22)>=Ввод!B18),"ЧАСТИЧНО ЗАКРЫТЬ","ДЕРЖАТЬ")) | P22: =IF(B22<>"Y",0,IFERROR((Ввод!B12-Расчеты!B3-Ввод!B15/2+Расчеты!B6)/(Расчеты!B4-Ввод!B12-Ввод!B15/2-Расчеты!B6),0)) | Q22: =IF(B22="Y",B22&C22,"")
J23: =IF(C23="BUY",Ввод!B13,Ввод!B14) | K23: =IF(C23="BUY",J23-E23,E23-J23) | L23: =IF(B23="Y",K23*D23*Ввод!B6+H23+I23,0) | M23: =IF(B23="Y",D23*Ввод!B6*J23/Ввод!B7,0) | N23: =IF(B23="Y",ROUND(MIN(D23*Ввод!B19,D23*0.5),2),0) | O23: =IF(B23<>"Y","НЕТ",IF(AND(Расчеты!B11="ДА",ABS(K23)>=Ввод!B18),"ЧАСТИЧНО ЗАКРЫТЬ","ДЕРЖАТЬ")) | P23: =IF(B23<>"Y",0,IFERROR((Ввод!B12-Расчеты!B3-Ввод!B15/2+Расчеты!B6)/(Расчеты!B4-Ввод!B12-Ввод!B15/2-Расчеты!B6),0)) | Q23: =IF(B23="Y",B23&C23,"")
J24: =IF(C24="BUY",Ввод!B13,Ввод!B14) | K24: =IF(C24="BUY",J24-E24,E24-J24) | L24: =IF(B24="Y",K24*D24*Ввод!B6+H24+I24,0) | M24: =IF(B24="Y",D24*Ввод!B6*J24/Ввод!B7,0) | N24: =IF(B24="Y",ROUND(MIN(D24*Ввод!B19,D24*0.5),2),0) | O24: =IF(B24<>"Y","НЕТ",IF(AND(Расчеты!B11="ДА",ABS(K24)>=Ввод!B18),"ЧАСТИЧНО ЗАКРЫТЬ","ДЕРЖАТЬ")) | P24: =IF(B24<>"Y",0,IFERROR((Ввод!B12-Расчеты!B3-Ввод!B15/2+Расчеты!B6)/(Расчеты!B4-Ввод!B12-Ввод!B15/2-Расчеты!B6),0)) | Q24: =IF(B24="Y",B24&C24,"")
J25: =IF(C25="BUY",Ввод!B13,Ввод!B14) | K25: =IF(C25="BUY",J25-E25,E25-J25) | L25: =IF(B25="Y",K25*D25*Ввод!B6+H25+I25,0) | M25: =IF(B25="Y",D25*Ввод!B6*J25/Ввод!B7,0) | N25: =IF(B25="Y",ROUND(MIN(D25*Ввод!B19,D25*0.5),2),0) | O25: =IF(B25<>"Y","НЕТ",IF(AND(Расчеты!B11="ДА",ABS(K25)>=Ввод!B18),"ЧАСТИЧНО ЗАКРЫТЬ","ДЕРЖАТЬ")) | P25: =IF(B25<>"Y",0,IFERROR((Ввод!B12-Расчеты!B3-Ввод!B15/2+Расчеты!B6)/(Расчеты!B4-Ввод!B12-Ввод!B15/2-Расчеты!B6),0)) | Q25: =IF(B25="Y",B25&C25,"")
J26: =IF(C26="BUY",Ввод!B13,Ввод!B14) | K26: =IF(C26="BUY",J26-E26,E26-J26) | L26: =IF(B26="Y",K26*D26*Ввод!B6+H26+I26,0) | M26: =IF(B26="Y",D26*Ввод!B6*J26/Ввод!B7,0) | N26: =IF(B26="Y",ROUND(MIN(D26*Ввод!B19,D26*0.5),2),0) | O26: =IF(B26<>"Y","НЕТ",IF(AND(Расчеты!B11="ДА",ABS(K26)>=Ввод!B18),"ЧАСТИЧНО ЗАКРЫТЬ","ДЕРЖАТЬ")) | P26: =IF(B26<>"Y",0,IFERROR((Ввод!B12-Расчеты!B3-Ввод!B15/2+Расчеты!B6)/(Расчеты!B4-Ввод!B12-Ввод!B15/2-Расчеты!B6),0)) | Q26: =IF(B26="Y",B26&C26,"")
J27: =IF(C27="BUY",Ввод!B13,Ввод!B14) | K27: =IF(C27="BUY",J27-E27,E27-J27) | L27: =IF(B27="Y",K27*D27*Ввод!B6+H27+I27,0) | M27: =IF(B27="Y",D27*Ввод!B6*J27/Ввод!B7,0) | N27: =IF(B27="Y",ROUND(MIN(D27*Ввод!B19,D27*0.5),2),0) | O27: =IF(B27<>"Y","НЕТ",IF(AND(Расчеты!B11="ДА",ABS(K27)>=Ввод!B18),"ЧАСТИЧНО ЗАКРЫТЬ","ДЕРЖАТЬ")) | P27: =IF(B27<>"Y",0,IFERROR((Ввод!B12-Расчеты!B3-Ввод!B15/2+Расчеты!B6)/(Расчеты!B4-Ввод!B12-Ввод!B15/2-Расчеты!B6),0)) | Q27: =IF(B27="Y",B27&C27,"")
J28: =IF(C28="BUY",Ввод!B13,Ввод!B14) | K28: =IF(C28="BUY",J28-E28,E28-J28) | L28: =IF(B28="Y",K28*D28*Ввод!B6+H28+I28,0) | M28: =IF(B28="Y",D28*Ввод!B6*J28/Ввод!B7,0) | N28: =IF(B28="Y",ROUND(MIN(D28*Ввод!B19,D28*0.5),2),0) | O28: =IF(B28<>"Y","НЕТ",IF(AND(Расчеты!B11="ДА",ABS(K28)>=Ввод!B18),"ЧАСТИЧНО ЗАКРЫТЬ","ДЕРЖАТЬ")) | P28: =IF(B28<>"Y",0,IFERROR((Ввод!B12-Расчеты!B3-Ввод!B15/2+Расчеты!B6)/(Расчеты!B4-Ввод!B12-Ввод!B15/2-Расчеты!B6),0)) | Q28: =IF(B28="Y",B28&C28,"")
J29: =IF(C29="BUY",Ввод!B13,Ввод!B14) | K29: =IF(C29="BUY",J29-E29,E29-J29) | L29: =IF(B29="Y",K29*D29*Ввод!B6+H29+I29,0) | M29: =IF(B29="Y",D29*Ввод!B6*J29/Ввод!B7,0) | N29: =IF(B29="Y",ROUND(MIN(D29*Ввод!B19,D29*0.5),2),0) | O29: =IF(B29<>"Y","НЕТ",IF(AND(Расчеты!B11="ДА",ABS(K29)>=Ввод!B18),"ЧАСТИЧНО ЗАКРЫТЬ","ДЕРЖАТЬ")) | P29: =IF(B29<>"Y",0,IFERROR((Ввод!B12-Расчеты!B3-Ввод!B15/2+Расчеты!B6)/(Расчеты!B4-Ввод!B12-Ввод!B15/2-Расчеты!B6),0)) | Q29: =IF(B29="Y",B29&C29,"")
J30: =IF(C30="BUY",Ввод!B13,Ввод!B14) | K30: =IF(C30="BUY",J30-E30,E30-J30) | L30: =IF(B30="Y",K30*D30*Ввод!B6+H30+I30,0) | M30: =IF(B30="Y",D30*Ввод!B6*J30/Ввод!B7,0) | N30: =IF(B30="Y",ROUND(MIN(D30*Ввод!B19,D30*0.5),2),0) | O30: =IF(B30<>"Y","НЕТ",IF(AND(Расчеты!B11="ДА",ABS(K30)>=Ввод!B18),"ЧАСТИЧНО ЗАКРЫТЬ","ДЕРЖАТЬ")) | P30: =IF(B30<>"Y",0,IFERROR((Ввод!B12-Расчеты!B3-Ввод!B15/2+Расчеты!B6)/(Расчеты!B4-Ввод!B12-Ввод!B15/2-Расчеты!B6),0)) | Q30: =IF(B30="Y",B30&C30,"")
J31: =IF(C31="BUY",Ввод!B13,Ввод!B14) | K31: =IF(C31="BUY",J31-E31,E31-J31) | L31: =IF(B31="Y",K31*D31*Ввод!B6+H31+I31,0) | M31: =IF(B31="Y",D31*Ввод!B6*J31/Ввод!B7,0) | N31: =IF(B31="Y",ROUND(MIN(D31*Ввод!B19,D31*0.5),2),0) | O31: =IF(B31<>"Y","НЕТ",IF(AND(Расчеты!B11="ДА",ABS(K31)>=Ввод!B18),"ЧАСТИЧНО ЗАКРЫТЬ","ДЕРЖАТЬ")) | P31: =IF(B31<>"Y",0,IFERROR((Ввод!B12-Расчеты!B3-Ввод!B15/2+Расчеты!B6)/(Расчеты!B4-Ввод!B12-Ввод!B15/2-Расчеты!B6),0)) | Q31: =IF(B31="Y",B31&C31,"")
J32: =IF(C32="BUY",Ввод!B13,Ввод!B14) | K32: =IF(C32="BUY",J32-E32,E32-J32) | L32: =IF(B32="Y",K32*D32*Ввод!B6+H32+I32,0) | M32: =IF(B32="Y",D32*Ввод!B6*J32/Ввод!B7,0) | N32: =IF(B32="Y",ROUND(MIN(D32*Ввод!B19,D32*0.5),2),0) | O32: =IF(B32<>"Y","НЕТ",IF(AND(Расчеты!B11="ДА",ABS(K32)>=Ввод!B18),"ЧАСТИЧНО ЗАКРЫТЬ","ДЕРЖАТЬ")) | P32: =IF(B32<>"Y",0,IFERROR((Ввод!B12-Расчеты!B3-Ввод!B15/2+Расчеты!B6)/(Расчеты!B4-Ввод!B12-Ввод!B15/2-Расчеты!B6),0)) | Q32: =IF(B32="Y",B32&C32,"")
J33: =IF(C33="BUY",Ввод!B13,Ввод!B14) | K33: =IF(C33="BUY",J33-E33,E33-J33) | L33: =IF(B33="Y",K33*D33*Ввод!B6+H33+I33,0) | M33: =IF(B33="Y",D33*Ввод!B6*J33/Ввод!B7,0) | N33: =IF(B33="Y",ROUND(MIN(D33*Ввод!B19,D33*0.5),2),0) | O33: =IF(B33<>"Y","НЕТ",IF(AND(Расчеты!B11="ДА",ABS(K33)>=Ввод!B18),"ЧАСТИЧНО ЗАКРЫТЬ","ДЕРЖАТЬ")) | P33: =IF(B33<>"Y",0,IFERROR((Ввод!B12-Расчеты!B3-Ввод!B15/2+Расчеты!B6)/(Расчеты!B4-Ввод!B12-Ввод!B15/2-Расчеты!B6),0)) | Q33: =IF(B33="Y",B33&C33,"")
J34: =IF(C34="BUY",Ввод!B13,Ввод!B14) | K34: =IF(C34="BUY",J34-E34,E34-J34) | L34: =IF(B34="Y",K34*D34*Ввод!B6+H34+I34,0) | M34: =IF(B34="Y",D34*Ввод!B6*J34/Ввод!B7,0) | N34: =IF(B34="Y",ROUND(MIN(D34*Ввод!B19,D34*0.5),2),0) | O34: =IF(B34<>"Y","НЕТ",IF(AND(Расчеты!B11="ДА",ABS(K34)>=Ввод!B18),"ЧАСТИЧНО ЗАКРЫТЬ","ДЕРЖАТЬ")) | P34: =IF(B34<>"Y",0,IFERROR((Ввод!B12-Расчеты!B3-Ввод!B15/2+Расчеты!B6)/(Расчеты!B4-Ввод!B12-Ввод!B15/2-Расчеты!B6),0)) | Q34: =IF(B34="Y",B34&C34,"")
J35: =IF(C35="BUY",Ввод!B13,Ввод!B14) | K35: =IF(C35="BUY",J35-E35,E35-J35) | L35: =IF(B35="Y",K35*D35*Ввод!B6+H35+I35,0) | M35: =IF(B35="Y",D35*Ввод!B6*J35/Ввод!B7,0) | N35: =IF(B35="Y",ROUND(MIN(D35*Ввод!B19,D35*0.5),2),0) | O35: =IF(B35<>"Y","НЕТ",IF(AND(Расчеты!B11="ДА",ABS(K35)>=Ввод!B18),"ЧАСТИЧНО ЗАКРЫТЬ","ДЕРЖАТЬ")) | P35: =IF(B35<>"Y",0,IFERROR((Ввод!B12-Расчеты!B3-Ввод!B15/2+Расчеты!B6)/(Расчеты!B4-Ввод!B12-Ввод!B15/2-Расчеты!B6),0)) | Q35: =IF(B35="Y",B35&C35,"")
J36: =IF(C36="BUY",Ввод!B13,Ввод!B14) | K36: =IF(C36="BUY",J36-E36,E36-J36) | L36: =IF(B36="Y",K36*D36*Ввод!B6+H36+I36,0) | M36: =IF(B36="Y",D36*Ввод!B6*J36/Ввод!B7,0) | N36: =IF(B36="Y",ROUND(MIN(D36*Ввод!B19,D36*0.5),2),0) | O36: =IF(B36<>"Y","НЕТ",IF(AND(Расчеты!B11="ДА",ABS(K36)>=Ввод!B18),"ЧАСТИЧНО ЗАКРЫТЬ","ДЕРЖАТЬ")) | P36: =IF(B36<>"Y",0,IFERROR((Ввод!B12-Расчеты!B3-Ввод!B15/2+Расчеты!B6)/(Расчеты!B4-Ввод!B12-Ввод!B15/2-Расчеты!B6),0)) | Q36: =IF(B36="Y",B36&C36,"")
J37: =IF(C37="BUY",Ввод!B13,Ввод!B14) | K37: =IF(C37="BUY",J37-E37,E37-J37) | L37: =IF(B37="Y",K37*D37*Ввод!B6+H37+I37,0) | M37: =IF(B37="Y",D37*Ввод!B6*J37/Ввод!B7,0) | N37: =IF(B37="Y",ROUND(MIN(D37*Ввод!B19,D37*0.5),2),0) | O37: =IF(B37<>"Y","НЕТ",IF(AND(Расчеты!B11="ДА",ABS(K37)>=Ввод!B18),"ЧАСТИЧНО ЗАКРЫТЬ","ДЕРЖАТЬ")) | P37: =IF(B37<>"Y",0,IFERROR((Ввод!B12-Расчеты!B3-Ввод!B15/2+Расчеты!B6)/(Расчеты!B4-Ввод!B12-Ввод!B15/2-Расчеты!B6),0)) | Q37: =IF(B37="Y",B37&C37,"")
J38: =IF(C38="BUY",Ввод!B13,Ввод!B14) | K38: =IF(C38="BUY",J38-E38,E38-J38) | L38: =IF(B38="Y",K38*D38*Ввод!B6+H38+I38,0) | M38: =IF(B38="Y",D38*Ввод!B6*J38/Ввод!B7,0) | N38: =IF(B38="Y",ROUND(MIN(D38*Ввод!B19,D38*0.5),2),0) | O38: =IF(B38<>"Y","НЕТ",IF(AND(Расчеты!B11="ДА",ABS(K38)>=Ввод!B18),"ЧАСТИЧНО ЗАКРЫТЬ","ДЕРЖАТЬ")) | P38: =IF(B38<>"Y",0,IFERROR((Ввод!B12-Расчеты!B3-Ввод!B15/2+Расчеты!B6)/(Расчеты!B4-Ввод!B12-Ввод!B15/2-Расчеты!B6),0)) | Q38: =IF(B38="Y",B38&C38,"")
J39: =IF(C39="BUY",Ввод!B13,Ввод!B14) | K39: =IF(C39="BUY",J39-E39,E39-J39) | L39: =IF(B39="Y",K39*D39*Ввод!B6+H39+I39,0) | M39: =IF(B39="Y",D39*Ввод!B6*J39/Ввод!B7,0) | N39: =IF(B39="Y",ROUND(MIN(D39*Ввод!B19,D39*0.5),2),0) | O39: =IF(B39<>"Y","НЕТ",IF(AND(Расчеты!B11="ДА",ABS(K39)>=Ввод!B18),"ЧАСТИЧНО ЗАКРЫТЬ","ДЕРЖАТЬ")) | P39: =IF(B39<>"Y",0,IFERROR((Ввод!B12-Расчеты!B3-Ввод!B15/2+Расчеты!B6)/(Расчеты!B4-Ввод!B12-Ввод!B15/2-Расчеты!B6),0)) | Q39: =IF(B39="Y",B39&C39,"")
J40: =IF(C40="BUY",Ввод!B13,Ввод!B14) | K40: =IF(C40="BUY",J40-E40,E40-J40) | L40: =IF(B40="Y",K40*D40*Ввод!B6+H40+I40,0) | M40: =IF(B40="Y",D40*Ввод!B6*J40/Ввод!B7,0) | N40: =IF(B40="Y",ROUND(MIN(D40*Ввод!B19,D40*0.5),2),0) | O40: =IF(B40<>"Y","НЕТ",IF(AND(Расчеты!B11="ДА",ABS(K40)>=Ввод!B18),"ЧАСТИЧНО ЗАКРЫТЬ","ДЕРЖАТЬ")) | P40: =IF(B40<>"Y",0,IFERROR((Ввод!B12-Расчеты!B3-Ввод!B15/2+Расчеты!B6)/(Расчеты!B4-Ввод!B12-Ввод!B15/2-Расчеты!B6),0)) | Q40: =IF(B40="Y",B40&C40,"")
J41: =IF(C41="BUY",Ввод!B13,Ввод!B14) | K41: =IF(C41="BUY",J41-E41,E41-J41) | L41: =IF(B41="Y",K41*D41*Ввод!B6+H41+I41,0) | M41: =IF(B41="Y",D41*Ввод!B6*J41/Ввод!B7,0) | N41: =IF(B41="Y",ROUND(MIN(D41*Ввод!B19,D41*0.5),2),0) | O41: =IF(B41<>"Y","НЕТ",IF(AND(Расчеты!B11="ДА",ABS(K41)>=Ввод!B18),"ЧАСТИЧНО ЗАКРЫТЬ","ДЕРЖАТЬ")) | P41: =IF(B41<>"Y",0,IFERROR((Ввод!B12-Расчеты!B3-Ввод!B15/2+Расчеты!B6)/(Расчеты!B4-Ввод!B12-Ввод!B15/2-Расчеты!B6),0)) | Q41: =IF(B41="Y",B41&C41,"")
J42: =IF(C42="BUY",Ввод!B13,Ввод!B14) | K42: =IF(C42="BUY",J42-E42,E42-J42) | L42: =IF(B42="Y",K42*D42*Ввод!B6+H42+I42,0) | M42: =IF(B42="Y",D42*Ввод!B6*J42/Ввод!B7,0) | N42: =IF(B42="Y",ROUND(MIN(D42*Ввод!B19,D42*0.5),2),0) | O42: =IF(B42<>"Y","НЕТ",IF(AND(Расчеты!B11="ДА",ABS(K42)>=Ввод!B18),"ЧАСТИЧНО ЗАКРЫТЬ","ДЕРЖАТЬ")) | P42: =IF(B42<>"Y",0,IFERROR((Ввод!B12-Расчеты!B3-Ввод!B15/2+Расчеты!B6)/(Расчеты!B4-Ввод!B12-Ввод!B15/2-Расчеты!B6),0)) | Q42: =IF(B42="Y",B42&C42,"")
J43: =IF(C43="BUY",Ввод!B13,Ввод!B14) | K43: =IF(C43="BUY",J43-E43,E43-J43) | L43: =IF(B43="Y",K43*D43*Ввод!B6+H43+I43,0) | M43: =IF(B43="Y",D43*Ввод!B6*J43/Ввод!B7,0) | N43: =IF(B43="Y",ROUND(MIN(D43*Ввод!B19,D43*0.5),2),0) | O43: =IF(B43<>"Y","НЕТ",IF(AND(Расчеты!B11="ДА",ABS(K43)>=Ввод!B18),"ЧАСТИЧНО ЗАКРЫТЬ","ДЕРЖАТЬ")) | P43: =IF(B43<>"Y",0,IFERROR((Ввод!B12-Расчеты!B3-Ввод!B15/2+Расчеты!B6)/(Расчеты!B4-Ввод!B12-Ввод!B15/2-Расчеты!B6),0)) | Q43: =IF(B43="Y",B43&C43,"")
J44: =IF(C44="BUY",Ввод!B13,Ввод!B14) | K44: =IF(C44="BUY",J44-E44,E44-J44) | L44: =IF(B44="Y",K44*D44*Ввод!B6+H44+I44,0) | M44: =IF(B44="Y",D44*Ввод!B6*J44/Ввод!B7,0) | N44: =IF(B44="Y",ROUND(MIN(D44*Ввод!B19,D44*0.5),2),0) | O44: =IF(B44<>"Y","НЕТ",IF(AND(Расчеты!B11="ДА",ABS(K44)>=Ввод!B18),"ЧАСТИЧНО ЗАКРЫТЬ","ДЕРЖАТЬ")) | P44: =IF(B44<>"Y",0,IFERROR((Ввод!B12-Расчеты!B3-Ввод!B15/2+Расчеты!B6)/(Расчеты!B4-Ввод!B12-Ввод!B15/2-Расчеты!B6),0)) | Q44: =IF(B44="Y",B44&C44,"")
J45: =IF(C45="BUY",Ввод!B13,Ввод!B14) | K45: =IF(C45="BUY",J45-E45,E45-J45) | L45: =IF(B45="Y",K45*D45*Ввод!B6+H45+I45,0) | M45: =IF(B45="Y",D45*Ввод!B6*J45/Ввод!B7,0) | N45: =IF(B45="Y",ROUND(MIN(D45*Ввод!B19,D45*0.5),2),0) | O45: =IF(B45<>"Y","НЕТ",IF(AND(Расчеты!B11="ДА",ABS(K45)>=Ввод!B18),"ЧАСТИЧНО ЗАКРЫТЬ","ДЕРЖАТЬ")) | P45: =IF(B45<>"Y",0,IFERROR((Ввод!B12-Расчеты!B3-Ввод!B15/2+Расчеты!B6)/(Расчеты!B4-Ввод!B12-Ввод!B15/2-Расчеты!B6),0)) | Q45: =IF(B45="Y",B45&C45,"")
J46: =IF(C46="BUY",Ввод!B13,Ввод!B14) | K46: =IF(C46="BUY",J46-E46,E46-J46) | L46: =IF(B46="Y",K46*D46*Ввод!B6+H46+I46,0) | M46: =IF(B46="Y",D46*Ввод!B6*J46/Ввод!B7,0) | N46: =IF(B46="Y",ROUND(MIN(D46*Ввод!B19,D46*0.5),2),0) | O46: =IF(B46<>"Y","НЕТ",IF(AND(Расчеты!B11="ДА",ABS(K46)>=Ввод!B18),"ЧАСТИЧНО ЗАКРЫТЬ","ДЕРЖАТЬ")) | P46: =IF(B46<>"Y",0,IFERROR((Ввод!B12-Расчеты!B3-Ввод!B15/2+Расчеты!B6)/(Расчеты!B4-Ввод!B12-Ввод!B15/2-Расчеты!B6),0)) | Q46: =IF(B46="Y",B46&C46,"")
J47: =IF(C47="BUY",Ввод!B13,Ввод!B14) | K47: =IF(C47="BUY",J47-E47,E47-J47) | L47: =IF(B47="Y",K47*D47*Ввод!B6+H47+I47,0) | M47: =IF(B47="Y",D47*Ввод!B6*J47/Ввод!B7,0) | N47: =IF(B47="Y",ROUND(MIN(D47*Ввод!B19,D47*0.5),2),0) | O47: =IF(B47<>"Y","НЕТ",IF(AND(Расчеты!B11="ДА",ABS(K47)>=Ввод!B18),"ЧАСТИЧНО ЗАКРЫТЬ","ДЕРЖАТЬ")) | P47: =IF(B47<>"Y",0,IFERROR((Ввод!B12-Расчеты!B3-Ввод!B15/2+Расчеты!B6)/(Расчеты!B4-Ввод!B12-Ввод!B15/2-Расчеты!B6),0)) | Q47: =IF(B47="Y",B47&C47,"")
J48: =IF(C48="BUY",Ввод!B13,Ввод!B14) | K48: =IF(C48="BUY",J48-E48,E48-J48) | L48: =IF(B48="Y",K48*D48*Ввод!B6+H48+I48,0) | M48: =IF(B48="Y",D48*Ввод!B6*J48/Ввод!B7,0) | N48: =IF(B48="Y",ROUND(MIN(D48*Ввод!B19,D48*0.5),2),0) | O48: =IF(B48<>"Y","НЕТ",IF(AND(Расчеты!B11="ДА",ABS(K48)>=Ввод!B18),"ЧАСТИЧНО ЗАКРЫТЬ","ДЕРЖАТЬ")) | P48: =IF(B48<>"Y",0,IFERROR((Ввод!B12-Расчеты!B3-Ввод!B15/2+Расчеты!B6)/(Расчеты!B4-Ввод!B12-Ввод!B15/2-Расчеты!B6),0)) | Q48: =IF(B48="Y",B48&C48,"")
J49: =IF(C49="BUY",Ввод!B13,Ввод!B14) | K49: =IF(C49="BUY",J49-E49,E49-J49) | L49: =IF(B49="Y",K49*D49*Ввод!B6+H49+I49,0) | M49: =IF(B49="Y",D49*Ввод!B6*J49/Ввод!B7,0) | N49: =IF(B49="Y",ROUND(MIN(D49*Ввод!B19,D49*0.5),2),0) | O49: =IF(B49<>"Y","НЕТ",IF(AND(Расчеты!B11="ДА",ABS(K49)>=Ввод!B18),"ЧАСТИЧНО ЗАКРЫТЬ","ДЕРЖАТЬ")) | P49: =IF(B49<>"Y",0,IFERROR((Ввод!B12-Расчеты!B3-Ввод!B15/2+Расчеты!B6)/(Расчеты!B4-Ввод!B12-Ввод!B15/2-Расчеты!B6),0)) | Q49: =IF(B49="Y",B49&C49,"")
J50: =IF(C50="BUY",Ввод!B13,Ввод!B14) | K50: =IF(C50="BUY",J50-E50,E50-J50) | L50: =IF(B50="Y",K50*D50*Ввод!B6+H50+I50,0) | M50: =IF(B50="Y",D50*Ввод!B6*J50/Ввод!B7,0) | N50: =IF(B50="Y",ROUND(MIN(D50*Ввод!B19,D50*0.5),2),0) | O50: =IF(B50<>"Y","НЕТ",IF(AND(Расчеты!B11="ДА",ABS(K50)>=Ввод!B18),"ЧАСТИЧНО ЗАКРЫТЬ","ДЕРЖАТЬ")) | P50: =IF(B50<>"Y",0,IFERROR((Ввод!B12-Расчеты!B3-Ввод!B15/2+Расчеты!B6)/(Расчеты!B4-Ввод!B12-Ввод!B15/2-Расчеты!B6),0)) | Q50: =IF(B50="Y",B50&C50,"")
J51: =IF(C51="BUY",Ввод!B13,Ввод!B14) | K51: =IF(C51="BUY",J51-E51,E51-J51) | L51: =IF(B51="Y",K51*D51*Ввод!B6+H51+I51,0) | M51: =IF(B51="Y",D51*Ввод!B6*J51/Ввод!B7,0) | N51: =IF(B51="Y",ROUND(MIN(D51*Ввод!B19,D51*0.5),2),0) | O51: =IF(B51<>"Y","НЕТ",IF(AND(Расчеты!B11="ДА",ABS(K51)>=Ввод!B18),"ЧАСТИЧНО ЗАКРЫТЬ","ДЕРЖАТЬ")) | P51: =IF(B51<>"Y",0,IFERROR((Ввод!B12-Расчеты!B3-Ввод!B15/2+Расчеты!B6)/(Расчеты!B4-Ввод!B12-Ввод!B15/2-Расчеты!B6),0)) | Q51: =IF(B51="Y",B51&C51,"")
J52: =IF(C52="BUY",Ввод!B13,Ввод!B14) | K52: =IF(C52="BUY",J52-E52,E52-J52) | L52: =IF(B52="Y",K52*D52*Ввод!B6+H52+I52,0) | M52: =IF(B52="Y",D52*Ввод!B6*J52/Ввод!B7,0) | N52: =IF(B52="Y",ROUND(MIN(D52*Ввод!B19,D52*0.5),2),0) | O52: =IF(B52<>"Y","НЕТ",IF(AND(Расчеты!B11="ДА",ABS(K52)>=Ввод!B18),"ЧАСТИЧНО ЗАКРЫТЬ","ДЕРЖАТЬ")) | P52: =IF(B52<>"Y",0,IFERROR((Ввод!B12-Расчеты!B3-Ввод!B15/2+Расчеты!B6)/(Расчеты!B4-Ввод!B12-Ввод!B15/2-Расчеты!B6),0)) | Q52: =IF(B52="Y",B52&C52,"")
J53: =IF(C53="BUY",Ввод!B13,Ввод!B14) | K53: =IF(C53="BUY",J53-E53,E53-J53) | L53: =IF(B53="Y",K53*D53*Ввод!B6+H53+I53,0) | M53: =IF(B53="Y",D53*Ввод!B6*J53/Ввод!B7,0) | N53: =IF(B53="Y",ROUND(MIN(D53*Ввод!B19,D53*0.5),2),0) | O53: =IF(B53<>"Y","НЕТ",IF(AND(Расчеты!B11="ДА",ABS(K53)>=Ввод!B18),"ЧАСТИЧНО ЗАКРЫТЬ","ДЕРЖАТЬ")) | P53: =IF(B53<>"Y",0,IFERROR((Ввод!B12-Расчеты!B3-Ввод!B15/2+Расчеты!B6)/(Расчеты!B4-Ввод!B12-Ввод!B15/2-Расчеты!B6),0)) | Q53: =IF(B53="Y",B53&C53,"")
J54: =IF(C54="BUY",Ввод!B13,Ввод!B14) | K54: =IF(C54="BUY",J54-E54,E54-J54) | L54: =IF(B54="Y",K54*D54*Ввод!B6+H54+I54,0) | M54: =IF(B54="Y",D54*Ввод!B6*J54/Ввод!B7,0) | N54: =IF(B54="Y",ROUND(MIN(D54*Ввод!B19,D54*0.5),2),0) | O54: =IF(B54<>"Y","НЕТ",IF(AND(Расчеты!B11="ДА",ABS(K54)>=Ввод!B18),"ЧАСТИЧНО ЗАКРЫТЬ","ДЕРЖАТЬ")) | P54: =IF(B54<>"Y",0,IFERROR((Ввод!B12-Расчеты!B3-Ввод!B15/2+Расчеты!B6)/(Расчеты!B4-Ввод!B12-Ввод!B15/2-Расчеты!B6),0)) | Q54: =IF(B54="Y",B54&C54,"")
J55: =IF(C55="BUY",Ввод!B13,Ввод!B14) | K55: =IF(C55="BUY",J55-E55,E55-J55) | L55: =IF(B55="Y",K55*D55*Ввод!B6+H55+I55,0) | M55: =IF(B55="Y",D55*Ввод!B6*J55/Ввод!B7,0) | N55: =IF(B55="Y",ROUND(MIN(D55*Ввод!B19,D55*0.5),2),0) | O55: =IF(B55<>"Y","НЕТ",IF(AND(Расчеты!B11="ДА",ABS(K55)>=Ввод!B18),"ЧАСТИЧНО ЗАКРЫТЬ","ДЕРЖАТЬ")) | P55: =IF(B55<>"Y",0,IFERROR((Ввод!B12-Расчеты!B3-Ввод!B15/2+Расчеты!B6)/(Расчеты!B4-Ввод!B12-Ввод!B15/2-Расчеты!B6),0)) | Q55: =IF(B55="Y",B55&C55,"")
J56: =IF(C56="BUY",Ввод!B13,Ввод!B14) | K56: =IF(C56="BUY",J56-E56,E56-J56) | L56: =IF(B56="Y",K56*D56*Ввод!B6+H56+I56,0) | M56: =IF(B56="Y",D56*Ввод!B6*J56/Ввод!B7,0) | N56: =IF(B56="Y",ROUND(MIN(D56*Ввод!B19,D56*0.5),2),0) | O56: =IF(B56<>"Y","НЕТ",IF(AND(Расчеты!B11="ДА",ABS(K56)>=Ввод!B18),"ЧАСТИЧНО ЗАКРЫТЬ","ДЕРЖАТЬ")) | P56: =IF(B56<>"Y",0,IFERROR((Ввод!B12-Расчеты!B3-Ввод!B15/2+Расчеты!B6)/(Расчеты!B4-Ввод!B12-Ввод!B15/2-Расчеты!B6),0)) | Q56: =IF(B56="Y",B56&C56,"")
J57: =IF(C57="BUY",Ввод!B13,Ввод!B14) | K57: =IF(C57="BUY",J57-E57,E57-J57) | L57: =IF(B57="Y",K57*D57*Ввод!B6+H57+I57,0) | M57: =IF(B57="Y",D57*Ввод!B6*J57/Ввод!B7,0) | N57: =IF(B57="Y",ROUND(MIN(D57*Ввод!B19,D57*0.5),2),0) | O57: =IF(B57<>"Y","НЕТ",IF(AND(Расчеты!B11="ДА",ABS(K57)>=Ввод!B18),"ЧАСТИЧНО ЗАКРЫТЬ","ДЕРЖАТЬ")) | P57: =IF(B57<>"Y",0,IFERROR((Ввод!B12-Расчеты!B3-Ввод!B15/2+Расчеты!B6)/(Расчеты!B4-Ввод!B12-Ввод!B15/2-Расчеты!B6),0)) | Q57: =IF(B57="Y",B57&C57,"")
J58: =IF(C58="BUY",Ввод!B13,Ввод!B14) | K58: =IF(C58="BUY",J58-E58,E58-J58) | L58: =IF(B58="Y",K58*D58*Ввод!B6+H58+I58,0) | M58: =IF(B58="Y",D58*Ввод!B6*J58/Ввод!B7,0) | N58: =IF(B58="Y",ROUND(MIN(D58*Ввод!B19,D58*0.5),2),0) | O58: =IF(B58<>"Y","НЕТ",IF(AND(Расчеты!B11="ДА",ABS(K58)>=Ввод!B18),"ЧАСТИЧНО ЗАКРЫТЬ","ДЕРЖАТЬ")) | P58: =IF(B58<>"Y",0,IFERROR((Ввод!B12-Расчеты!B3-Ввод!B15/2+Расчеты!B6)/(Расчеты!B4-Ввод!B12-Ввод!B15/2-Расчеты!B6),0)) | Q58: =IF(B58="Y",B58&C58,"")
J59: =IF(C59="BUY",Ввод!B13,Ввод!B14) | K59: =IF(C59="BUY",J59-E59,E59-J59) | L59: =IF(B59="Y",K59*D59*Ввод!B6+H59+I59,0) | M59: =IF(B59="Y",D59*Ввод!B6*J59/Ввод!B7,0) | N59: =IF(B59="Y",ROUND(MIN(D59*Ввод!B19,D59*0.5),2),0) | O59: =IF(B59<>"Y","НЕТ",IF(AND(Расчеты!B11="ДА",ABS(K59)>=Ввод!B18),"ЧАСТИЧНО ЗАКРЫТЬ","ДЕРЖАТЬ")) | P59: =IF(B59<>"Y",0,IFERROR((Ввод!B12-Расчеты!B3-Ввод!B15/2+Расчеты!B6)/(Расчеты!B4-Ввод!B12-Ввод!B15/2-Расчеты!B6),0)) | Q59: =IF(B59="Y",B59&C59,"")
J60: =IF(C60="BUY",Ввод!B13,Ввод!B14) | K60: =IF(C60="BUY",J60-E60,E60-J60) | L60: =IF(B60="Y",K60*D60*Ввод!B6+H60+I60,0) | M60: =IF(B60="Y",D60*Ввод!B6*J60/Ввод!B7,0) | N60: =IF(B60="Y",ROUND(MIN(D60*Ввод!B19,D60*0.5),2),0) | O60: =IF(B60<>"Y","НЕТ",IF(AND(Расчеты!B11="ДА",ABS(K60)>=Ввод!B18),"ЧАСТИЧНО ЗАКРЫТЬ","ДЕРЖАТЬ")) | P60: =IF(B60<>"Y",0,IFERROR((Ввод!B12-Расчеты!B3-Ввод!B15/2+Расчеты!B6)/(Расчеты!B4-Ввод!B12-Ввод!B15/2-Расчеты!B6),0)) | Q60: =IF(B60="Y",B60&C60,"")
J61: =IF(C61="BUY",Ввод!B13,Ввод!B14) | K61: =IF(C61="BUY",J61-E61,E61-J61) | L61: =IF(B61="Y",K61*D61*Ввод!B6+H61+I61,0) | M61: =IF(B61="Y",D61*Ввод!B6*J61/Ввод!B7,0) | N61: =IF(B61="Y",ROUND(MIN(D61*Ввод!B19,D61*0.5),2),0) | O61: =IF(B61<>"Y","НЕТ",IF(AND(Расчеты!B11="ДА",ABS(K61)>=Ввод!B18),"ЧАСТИЧНО ЗАКРЫТЬ","ДЕРЖАТЬ")) | P61: =IF(B61<>"Y",0,IFERROR((Ввод!B12-Расчеты!B3-Ввод!B15/2+Расчеты!B6)/(Расчеты!B4-Ввод!B12-Ввод!B15/2-Расчеты!B6),0)) | Q61: =IF(B61="Y",B61&C61,"")
J62: =IF(C62="BUY",Ввод!B13,Ввод!B14) | K62: =IF(C62="BUY",J62-E62,E62-J62) | L62: =IF(B62="Y",K62*D62*Ввод!B6+H62+I62,0) | M62: =IF(B62="Y",D62*Ввод!B6*J62/Ввод!B7,0) | N62: =IF(B62="Y",ROUND(MIN(D62*Ввод!B19,D62*0.5),2),0) | O62: =IF(B62<>"Y","НЕТ",IF(AND(Расчеты!B11="ДА",ABS(K62)>=Ввод!B18),"ЧАСТИЧНО ЗАКРЫТЬ","ДЕРЖАТЬ")) | P62: =IF(B62<>"Y",0,IFERROR((Ввод!B12-Расчеты!B3-Ввод!B15/2+Расчеты!B6)/(Расчеты!B4-Ввод!B12-Ввод!B15/2-Расчеты!B6),0)) | Q62: =IF(B62="Y",B62&C62,"")
J63: =IF(C63="BUY",Ввод!B13,Ввод!B14) | K63: =IF(C63="BUY",J63-E63,E63-J63) | L63: =IF(B63="Y",K63*D63*Ввод!B6+H63+I63,0) | M63: =IF(B63="Y",D63*Ввод!B6*J63/Ввод!B7,0) | N63: =IF(B63="Y",ROUND(MIN(D63*Ввод!B19,D63*0.5),2),0) | O63: =IF(B63<>"Y","НЕТ",IF(AND(Расчеты!B11="ДА",ABS(K63)>=Ввод!B18),"ЧАСТИЧНО ЗАКРЫТЬ","ДЕРЖАТЬ")) | P63: =IF(B63<>"Y",0,IFERROR((Ввод!B12-Расчеты!B3-Ввод!B15/2+Расчеты!B6)/(Расчеты!B4-Ввод!B12-Ввод!B15/2-Расчеты!B6),0)) | Q63: =IF(B63="Y",B63&C63,"")
J64: =IF(C64="BUY",Ввод!B13,Ввод!B14) | K64: =IF(C64="BUY",J64-E64,E64-J64) | L64: =IF(B64="Y",K64*D64*Ввод!B6+H64+I64,0) | M64: =IF(B64="Y",D64*Ввод!B6*J64/Ввод!B7,0) | N64: =IF(B64="Y",ROUND(MIN(D64*Ввод!B19,D64*0.5),2),0) | O64: =IF(B64<>"Y","НЕТ",IF(AND(Расчеты!B11="ДА",ABS(K64)>=Ввод!B18),"ЧАСТИЧНО ЗАКРЫТЬ","ДЕРЖАТЬ")) | P64: =IF(B64<>"Y",0,IFERROR((Ввод!B12-Расчеты!B3-Ввод!B15/2+Расчеты!B6)/(Расчеты!B4-Ввод!B12-Ввод!B15/2-Расчеты!B6),0)) | Q64: =IF(B64="Y",B64&C64,"")
J65: =IF(C65="BUY",Ввод!B13,Ввод!B14) | K65: =IF(C65="BUY",J65-E65,E65-J65) | L65: =IF(B65="Y",K65*D65*Ввод!B6+H65+I65,0) | M65: =IF(B65="Y",D65*Ввод!B6*J65/Ввод!B7,0) | N65: =IF(B65="Y",ROUND(MIN(D65*Ввод!B19,D65*0.5),2),0) | O65: =IF(B65<>"Y","НЕТ",IF(AND(Расчеты!B11="ДА",ABS(K65)>=Ввод!B18),"ЧАСТИЧНО ЗАКРЫТЬ","ДЕРЖАТЬ")) | P65: =IF(B65<>"Y",0,IFERROR((Ввод!B12-Расчеты!B3-Ввод!B15/2+Расчеты!B6)/(Расчеты!B4-Ввод!B12-Ввод!B15/2-Расчеты!B6),0)) | Q65: =IF(B65="Y",B65&C65,"")
J66: =IF(C66="BUY",Ввод!B13,Ввод!B14) | K66: =IF(C66="BUY",J66-E66,E66-J66) | L66: =IF(B66="Y",K66*D66*Ввод!B6+H66+I66,0) | M66: =IF(B66="Y",D66*Ввод!B6*J66/Ввод!B7,0) | N66: =IF(B66="Y",ROUND(MIN(D66*Ввод!B19,D66*0.5),2),0) | O66: =IF(B66<>"Y","НЕТ",IF(AND(Расчеты!B11="ДА",ABS(K66)>=Ввод!B18),"ЧАСТИЧНО ЗАКРЫТЬ","ДЕРЖАТЬ")) | P66: =IF(B66<>"Y",0,IFERROR((Ввод!B12-Расчеты!B3-Ввод!B15/2+Расчеты!B6)/(Расчеты!B4-Ввод!B12-Ввод!B15/2-Расчеты!B6),0)) | Q66: =IF(B66="Y",B66&C66,"")
J67: =IF(C67="BUY",Ввод!B13,Ввод!B14) | K67: =IF(C67="BUY",J67-E67,E67-J67) | L67: =IF(B67="Y",K67*D67*Ввод!B6+H67+I67,0) | M67: =IF(B67="Y",D67*Ввод!B6*J67/Ввод!B7,0) | N67: =IF(B67="Y",ROUND(MIN(D67*Ввод!B19,D67*0.5),2),0) | O67: =IF(B67<>"Y","НЕТ",IF(AND(Расчеты!B11="ДА",ABS(K67)>=Ввод!B18),"ЧАСТИЧНО ЗАКРЫТЬ","ДЕРЖАТЬ")) | P67: =IF(B67<>"Y",0,IFERROR((Ввод!B12-Расчеты!B3-Ввод!B15/2+Расчеты!B6)/(Расчеты!B4-Ввод!B12-Ввод!B15/2-Расчеты!B6),0)) | Q67: =IF(B67="Y",B67&C67,"")
J68: =IF(C68="BUY",Ввод!B13,Ввод!B14) | K68: =IF(C68="BUY",J68-E68,E68-J68) | L68: =IF(B68="Y",K68*D68*Ввод!B6+H68+I68,0) | M68: =IF(B68="Y",D68*Ввод!B6*J68/Ввод!B7,0) | N68: =IF(B68="Y",ROUND(MIN(D68*Ввод!B19,D68*0.5),2),0) | O68: =IF(B68<>"Y","НЕТ",IF(AND(Расчеты!B11="ДА",ABS(K68)>=Ввод!B18),"ЧАСТИЧНО ЗАКРЫТЬ","ДЕРЖАТЬ")) | P68: =IF(B68<>"Y",0,IFERROR((Ввод!B12-Расчеты!B3-Ввод!B15/2+Расчеты!B6)/(Расчеты!B4-Ввод!B12-Ввод!B15/2-Расчеты!B6),0)) | Q68: =IF(B68="Y",B68&C68,"")
J69: =IF(C69="BUY",Ввод!B13,Ввод!B14) | K69: =IF(C69="BUY",J69-E69,E69-J69) | L69: =IF(B69="Y",K69*D69*Ввод!B6+H69+I69,0) | M69: =IF(B69="Y",D69*Ввод!B6*J69/Ввод!B7,0) | N69: =IF(B69="Y",ROUND(MIN(D69*Ввод!B19,D69*0.5),2),0) | O69: =IF(B69<>"Y","НЕТ",IF(AND(Расчеты!B11="ДА",ABS(K69)>=Ввод!B18),"ЧАСТИЧНО ЗАКРЫТЬ","ДЕРЖАТЬ")) | P69: =IF(B69<>"Y",0,IFERROR((Ввод!B12-Расчеты!B3-Ввод!B15/2+Расчеты!B6)/(Расчеты!B4-Ввод!B12-Ввод!B15/2-Расчеты!B6),0)) | Q69: =IF(B69="Y",B69&C69,"")
J70: =IF(C70="BUY",Ввод!B13,Ввод!B14) | K70: =IF(C70="BUY",J70-E70,E70-J70) | L70: =IF(B70="Y",K70*D70*Ввод!B6+H70+I70,0) | M70: =IF(B70="Y",D70*Ввод!B6*J70/Ввод!B7,0) | N70: =IF(B70="Y",ROUND(MIN(D70*Ввод!B19,D70*0.5),2),0) | O70: =IF(B70<>"Y","НЕТ",IF(AND(Расчеты!B11="ДА",ABS(K70)>=Ввод!B18),"ЧАСТИЧНО ЗАКРЫТЬ","ДЕРЖАТЬ")) | P70: =IF(B70<>"Y",0,IFERROR((Ввод!B12-Расчеты!B3-Ввод!B15/2+Расчеты!B6)/(Расчеты!B4-Ввод!B12-Ввод!B15/2-Расчеты!B6),0)) | Q70: =IF(B70="Y",B70&C70,"")
J71: =IF(C71="BUY",Ввод!B13,Ввод!B14) | K71: =IF(C71="BUY",J71-E71,E71-J71) | L71: =IF(B71="Y",K71*D71*Ввод!B6+H71+I71,0) | M71: =IF(B71="Y",D71*Ввод!B6*J71/Ввод!B7,0) | N71: =IF(B71="Y",ROUND(MIN(D71*Ввод!B19,D71*0.5),2),0) | O71: =IF(B71<>"Y","НЕТ",IF(AND(Расчеты!B11="ДА",ABS(K71)>=Ввод!B18),"ЧАСТИЧНО ЗАКРЫТЬ","ДЕРЖАТЬ")) | P71: =IF(B71<>"Y",0,IFERROR((Ввод!B12-Расчеты!B3-Ввод!B15/2+Расчеты!B6)/(Расчеты!B4-Ввод!B12-Ввод!B15/2-Расчеты!B6),0)) | Q71: =IF(B71="Y",B71&C71,"")
J72: =IF(C72="BUY",Ввод!B13,Ввод!B14) | K72: =IF(C72="BUY",J72-E72,E72-J72) | L72: =IF(B72="Y",K72*D72*Ввод!B6+H72+I72,0) | M72: =IF(B72="Y",D72*Ввод!B6*J72/Ввод!B7,0) | N72: =IF(B72="Y",ROUND(MIN(D72*Ввод!B19,D72*0.5),2),0) | O72: =IF(B72<>"Y","НЕТ",IF(AND(Расчеты!B11="ДА",ABS(K72)>=Ввод!B18),"ЧАСТИЧНО ЗАКРЫТЬ","ДЕРЖАТЬ")) | P72: =IF(B72<>"Y",0,IFERROR((Ввод!B12-Расчеты!B3-Ввод!B15/2+Расчеты!B6)/(Расчеты!B4-Ввод!B12-Ввод!B15/2-Расчеты!B6),0)) | Q72: =IF(B72="Y",B72&C72,"")
J73: =IF(C73="BUY",Ввод!B13,Ввод!B14) | K73: =IF(C73="BUY",J73-E73,E73-J73) | L73: =IF(B73="Y",K73*D73*Ввод!B6+H73+I73,0) | M73: =IF(B73="Y",D73*Ввод!B6*J73/Ввод!B7,0) | N73: =IF(B73="Y",ROUND(MIN(D73*Ввод!B19,D73*0.5),2),0) | O73: =IF(B73<>"Y","НЕТ",IF(AND(Расчеты!B11="ДА",ABS(K73)>=Ввод!B18),"ЧАСТИЧНО ЗАКРЫТЬ","ДЕРЖАТЬ")) | P73: =IF(B73<>"Y",0,IFERROR((Ввод!B12-Расчеты!B3-Ввод!B15/2+Расчеты!B6)/(Расчеты!B4-Ввод!B12-Ввод!B15/2-Расчеты!B6),0)) | Q73: =IF(B73="Y",B73&C73,"")
J74: =IF(C74="BUY",Ввод!B13,Ввод!B14) | K74: =IF(C74="BUY",J74-E74,E74-J74) | L74: =IF(B74="Y",K74*D74*Ввод!B6+H74+I74,0) | M74: =IF(B74="Y",D74*Ввод!B6*J74/Ввод!B7,0) | N74: =IF(B74="Y",ROUND(MIN(D74*Ввод!B19,D74*0.5),2),0) | O74: =IF(B74<>"Y","НЕТ",IF(AND(Расчеты!B11="ДА",ABS(K74)>=Ввод!B18),"ЧАСТИЧНО ЗАКРЫТЬ","ДЕРЖАТЬ")) | P74: =IF(B74<>"Y",0,IFERROR((Ввод!B12-Расчеты!B3-Ввод!B15/2+Расчеты!B6)/(Расчеты!B4-Ввод!B12-Ввод!B15/2-Расчеты!B6),0)) | Q74: =IF(B74="Y",B74&C74,"")
J75: =IF(C75="BUY",Ввод!B13,Ввод!B14) | K75: =IF(C75="BUY",J75-E75,E75-J75) | L75: =IF(B75="Y",K75*D75*Ввод!B6+H75+I75,0) | M75: =IF(B75="Y",D75*Ввод!B6*J75/Ввод!B7,0) | N75: =IF(B75="Y",ROUND(MIN(D75*Ввод!B19,D75*0.5),2),0) | O75: =IF(B75<>"Y","НЕТ",IF(AND(Расчеты!B11="ДА",ABS(K75)>=Ввод!B18),"ЧАСТИЧНО ЗАКРЫТЬ","ДЕРЖАТЬ")) | P75: =IF(B75<>"Y",0,IFERROR((Ввод!B12-Расчеты!B3-Ввод!B15/2+Расчеты!B6)/(Расчеты!B4-Ввод!B12-Ввод!B15/2-Расчеты!B6),0)) | Q75: =IF(B75="Y",B75&C75,"")
J76: =IF(C76="BUY",Ввод!B13,Ввод!B14) | K76: =IF(C76="BUY",J76-E76,E76-J76) | L76: =IF(B76="Y",K76*D76*Ввод!B6+H76+I76,0) | M76: =IF(B76="Y",D76*Ввод!B6*J76/Ввод!B7,0) | N76: =IF(B76="Y",ROUND(MIN(D76*Ввод!B19,D76*0.5),2),0) | O76: =IF(B76<>"Y","НЕТ",IF(AND(Расчеты!B11="ДА",ABS(K76)>=Ввод!B18),"ЧАСТИЧНО ЗАКРЫТЬ","ДЕРЖАТЬ")) | P76: =IF(B76<>"Y",0,IFERROR((Ввод!B12-Расчеты!B3-Ввод!B15/2+Расчеты!B6)/(Расчеты!B4-Ввод!B12-Ввод!B15/2-Расчеты!B6),0)) | Q76: =IF(B76="Y",B76&C76,"")
J77: =IF(C77="BUY",Ввод!B13,Ввод!B14) | K77: =IF(C77="BUY",J77-E77,E77-J77) | L77: =IF(B77="Y",K77*D77*Ввод!B6+H77+I77,0) | M77: =IF(B77="Y",D77*Ввод!B6*J77/Ввод!B7,0) | N77: =IF(B77="Y",ROUND(MIN(D77*Ввод!B19,D77*0.5),2),0) | O77: =IF(B77<>"Y","НЕТ",IF(AND(Расчеты!B11="ДА",ABS(K77)>=Ввод!B18),"ЧАСТИЧНО ЗАКРЫТЬ","ДЕРЖАТЬ")) | P77: =IF(B77<>"Y",0,IFERROR((Ввод!B12-Расчеты!B3-Ввод!B15/2+Расчеты!B6)/(Расчеты!B4-Ввод!B12-Ввод!B15/2-Расчеты!B6),0)) | Q77: =IF(B77="Y",B77&C77,"")
J78: =IF(C78="BUY",Ввод!B13,Ввод!B14) | K78: =IF(C78="BUY",J78-E78,E78-J78) | L78: =IF(B78="Y",K78*D78*Ввод!B6+H78+I78,0) | M78: =IF(B78="Y",D78*Ввод!B6*J78/Ввод!B7,0) | N78: =IF(B78="Y",ROUND(MIN(D78*Ввод!B19,D78*0.5),2),0) | O78: =IF(B78<>"Y","НЕТ",IF(AND(Расчеты!B11="ДА",ABS(K78)>=Ввод!B18),"ЧАСТИЧНО ЗАКРЫТЬ","ДЕРЖАТЬ")) | P78: =IF(B78<>"Y",0,IFERROR((Ввод!B12-Расчеты!B3-Ввод!B15/2+Расчеты!B6)/(Расчеты!B4-Ввод!B12-Ввод!B15/2-Расчеты!B6),0)) | Q78: =IF(B78="Y",B78&C78,"")
J79: =IF(C79="BUY",Ввод!B13,Ввод!B14) | K79: =IF(C79="BUY",J79-E79,E79-J79) | L79: =IF(B79="Y",K79*D79*Ввод!B6+H79+I79,0) | M79: =IF(B79="Y",D79*Ввод!B6*J79/Ввод!B7,0) | N79: =IF(B79="Y",ROUND(MIN(D79*Ввод!B19,D79*0.5),2),0) | O79: =IF(B79<>"Y","НЕТ",IF(AND(Расчеты!B11="ДА",ABS(K79)>=Ввод!B18),"ЧАСТИЧНО ЗАКРЫТЬ","ДЕРЖАТЬ")) | P79: =IF(B79<>"Y",0,IFERROR((Ввод!B12-Расчеты!B3-Ввод!B15/2+Расчеты!B6)/(Расчеты!B4-Ввод!B12-Ввод!B15/2-Расчеты!B6),0)) | Q79: =IF(B79="Y",B79&C79,"")
J80: =IF(C80="BUY",Ввод!B13,Ввод!B14) | K80: =IF(C80="BUY",J80-E80,E80-J80) | L80: =IF(B80="Y",K80*D80*Ввод!B6+H80+I80,0) | M80: =IF(B80="Y",D80*Ввод!B6*J80/Ввод!B7,0) | N80: =IF(B80="Y",ROUND(MIN(D80*Ввод!B19,D80*0.5),2),0) | O80: =IF(B80<>"Y","НЕТ",IF(AND(Расчеты!B11="ДА",ABS(K80)>=Ввод!B18),"ЧАСТИЧНО ЗАКРЫТЬ","ДЕРЖАТЬ")) | P80: =IF(B80<>"Y",0,IFERROR((Ввод!B12-Расчеты!B3-Ввод!B15/2+Расчеты!B6)/(Расчеты!B4-Ввод!B12-Ввод!B15/2-Расчеты!B6),0)) | Q80: =IF(B80="Y",B80&C80,"")
J81: =IF(C81="BUY",Ввод!B13,Ввод!B14) | K81: =IF(C81="BUY",J81-E81,E81-J81) | L81: =IF(B81="Y",K81*D81*Ввод!B6+H81+I81,0) | M81: =IF(B81="Y",D81*Ввод!B6*J81/Ввод!B7,0) | N81: =IF(B81="Y",ROUND(MIN(D81*Ввод!B19,D81*0.5),2),0) | O81: =IF(B81<>"Y","НЕТ",IF(AND(Расчеты!B11="ДА",ABS(K81)>=Ввод!B18),"ЧАСТИЧНО ЗАКРЫТЬ","ДЕРЖАТЬ")) | P81: =IF(B81<>"Y",0,IFERROR((Ввод!B12-Расчеты!B3-Ввод!B15/2+Расчеты!B6)/(Расчеты!B4-Ввод!B12-Ввод!B15/2-Расчеты!B6),0)) | Q81: =IF(B81="Y",B81&C81,"")
J82: =IF(C82="BUY",Ввод!B13,Ввод!B14) | K82: =IF(C82="BUY",J82-E82,E82-J82) | L82: =IF(B82="Y",K82*D82*Ввод!B6+H82+I82,0) | M82: =IF(B82="Y",D82*Ввод!B6*J82/Ввод!B7,0) | N82: =IF(B82="Y",ROUND(MIN(D82*Ввод!B19,D82*0.5),2),0) | O82: =IF(B82<>"Y","НЕТ",IF(AND(Расчеты!B11="ДА",ABS(K82)>=Ввод!B18),"ЧАСТИЧНО ЗАКРЫТЬ","ДЕРЖАТЬ")) | P82: =IF(B82<>"Y",0,IFERROR((Ввод!B12-Расчеты!B3-Ввод!B15/2+Расчеты!B6)/(Расчеты!B4-Ввод!B12-Ввод!B15/2-Расчеты!B6),0)) | Q82: =IF(B82="Y",B82&C82,"")
J83: =IF(C83="BUY",Ввод!B13,Ввод!B14) | K83: =IF(C83="BUY",J83-E83,E83-J83) | L83: =IF(B83="Y",K83*D83*Ввод!B6+H83+I83,0) | M83: =IF(B83="Y",D83*Ввод!B6*J83/Ввод!B7,0) | N83: =IF(B83="Y",ROUND(MIN(D83*Ввод!B19,D83*0.5),2),0) | O83: =IF(B83<>"Y","НЕТ",IF(AND(Расчеты!B11="ДА",ABS(K83)>=Ввод!B18),"ЧАСТИЧНО ЗАКРЫТЬ","ДЕРЖАТЬ")) | P83: =IF(B83<>"Y",0,IFERROR((Ввод!B12-Расчеты!B3-Ввод!B15/2+Расчеты!B6)/(Расчеты!B4-Ввод!B12-Ввод!B15/2-Расчеты!B6),0)) | Q83: =IF(B83="Y",B83&C83,"")
J84: =IF(C84="BUY",Ввод!B13,Ввод!B14) | K84: =IF(C84="BUY",J84-E84,E84-J84) | L84: =IF(B84="Y",K84*D84*Ввод!B6+H84+I84,0) | M84: =IF(B84="Y",D84*Ввод!B6*J84/Ввод!B7,0) | N84: =IF(B84="Y",ROUND(MIN(D84*Ввод!B19,D84*0.5),2),0) | O84: =IF(B84<>"Y","НЕТ",IF(AND(Расчеты!B11="ДА",ABS(K84)>=Ввод!B18),"ЧАСТИЧНО ЗАКРЫТЬ","ДЕРЖАТЬ")) | P84: =IF(B84<>"Y",0,IFERROR((Ввод!B12-Расчеты!B3-Ввод!B15/2+Расчеты!B6)/(Расчеты!B4-Ввод!B12-Ввод!B15/2-Расчеты!B6),0)) | Q84: =IF(B84="Y",B84&C84,"")
J85: =IF(C85="BUY",Ввод!B13,Ввод!B14) | K85: =IF(C85="BUY",J85-E85,E85-J85) | L85: =IF(B85="Y",K85*D85*Ввод!B6+H85+I85,0) | M85: =IF(B85="Y",D85*Ввод!B6*J85/Ввод!B7,0) | N85: =IF(B85="Y",ROUND(MIN(D85*Ввод!B19,D85*0.5),2),0) | O85: =IF(B85<>"Y","НЕТ",IF(AND(Расчеты!B11="ДА",ABS(K85)>=Ввод!B18),"ЧАСТИЧНО ЗАКРЫТЬ","ДЕРЖАТЬ")) | P85: =IF(B85<>"Y",0,IFERROR((Ввод!B12-Расчеты!B3-Ввод!B15/2+Расчеты!B6)/(Расчеты!B4-Ввод!B12-Ввод!B15/2-Расчеты!B6),0)) | Q85: =IF(B85="Y",B85&C85,"")
J86: =IF(C86="BUY",Ввод!B13,Ввод!B14) | K86: =IF(C86="BUY",J86-E86,E86-J86) | L86: =IF(B86="Y",K86*D86*Ввод!B6+H86+I86,0) | M86: =IF(B86="Y",D86*Ввод!B6*J86/Ввод!B7,0) | N86: =IF(B86="Y",ROUND(MIN(D86*Ввод!B19,D86*0.5),2),0) | O86: =IF(B86<>"Y","НЕТ",IF(AND(Расчеты!B11="ДА",ABS(K86)>=Ввод!B18),"ЧАСТИЧНО ЗАКРЫТЬ","ДЕРЖАТЬ")) | P86: =IF(B86<>"Y",0,IFERROR((Ввод!B12-Расчеты!B3-Ввод!B15/2+Расчеты!B6)/(Расчеты!B4-Ввод!B12-Ввод!B15/2-Расчеты!B6),0)) | Q86: =IF(B86="Y",B86&C86,"")
J87: =IF(C87="BUY",Ввод!B13,Ввод!B14) | K87: =IF(C87="BUY",J87-E87,E87-J87) | L87: =IF(B87="Y",K87*D87*Ввод!B6+H87+I87,0) | M87: =IF(B87="Y",D87*Ввод!B6*J87/Ввод!B7,0) | N87: =IF(B87="Y",ROUND(MIN(D87*Ввод!B19,D87*0.5),2),0) | O87: =IF(B87<>"Y","НЕТ",IF(AND(Расчеты!B11="ДА",ABS(K87)>=Ввод!B18),"ЧАСТИЧНО ЗАКРЫТЬ","ДЕРЖАТЬ")) | P87: =IF(B87<>"Y",0,IFERROR((Ввод!B12-Расчеты!B3-Ввод!B15/2+Расчеты!B6)/(Расчеты!B4-Ввод!B12-Ввод!B15/2-Расчеты!B6),0)) | Q87: =IF(B87="Y",B87&C87,"")
J88: =IF(C88="BUY",Ввод!B13,Ввод!B14) | K88: =IF(C88="BUY",J88-E88,E88-J88) | L88: =IF(B88="Y",K88*D88*Ввод!B6+H88+I88,0) | M88: =IF(B88="Y",D88*Ввод!B6*J88/Ввод!B7,0) | N88: =IF(B88="Y",ROUND(MIN(D88*Ввод!B19,D88*0.5),2),0) | O88: =IF(B88<>"Y","НЕТ",IF(AND(Расчеты!B11="ДА",ABS(K88)>=Ввод!B18),"ЧАСТИЧНО ЗАКРЫТЬ","ДЕРЖАТЬ")) | P88: =IF(B88<>"Y",0,IFERROR((Ввод!B12-Расчеты!B3-Ввод!B15/2+Расчеты!B6)/(Расчеты!B4-Ввод!B12-Ввод!B15/2-Расчеты!B6),0)) | Q88: =IF(B88="Y",B88&C88,"")
J89: =IF(C89="BUY",Ввод!B13,Ввод!B14) | K89: =IF(C89="BUY",J89-E89,E89-J89) | L89: =IF(B89="Y",K89*D89*Ввод!B6+H89+I89,0) | M89: =IF(B89="Y",D89*Ввод!B6*J89/Ввод!B7,0) | N89: =IF(B89="Y",ROUND(MIN(D89*Ввод!B19,D89*0.5),2),0) | O89: =IF(B89<>"Y","НЕТ",IF(AND(Расчеты!B11="ДА",ABS(K89)>=Ввод!B18),"ЧАСТИЧНО ЗАКРЫТЬ","ДЕРЖАТЬ")) | P89: =IF(B89<>"Y",0,IFERROR((Ввод!B12-Расчеты!B3-Ввод!B15/2+Расчеты!B6)/(Расчеты!B4-Ввод!B12-Ввод!B15/2-Расчеты!B6),0)) | Q89: =IF(B89="Y",B89&C89,"")
J90: =IF(C90="BUY",Ввод!B13,Ввод!B14) | K90: =IF(C90="BUY",J90-E90,E90-J90) | L90: =IF(B90="Y",K90*D90*Ввод!B6+H90+I90,0) | M90: =IF(B90="Y",D90*Ввод!B6*J90/Ввод!B7,0) | N90: =IF(B90="Y",ROUND(MIN(D90*Ввод!B19,D90*0.5),2),0) | O90: =IF(B90<>"Y","НЕТ",IF(AND(Расчеты!B11="ДА",ABS(K90)>=Ввод!B18),"ЧАСТИЧНО ЗАКРЫТЬ","ДЕРЖАТЬ")) | P90: =IF(B90<>"Y",0,IFERROR((Ввод!B12-Расчеты!B3-Ввод!B15/2+Расчеты!B6)/(Расчеты!B4-Ввод!B12-Ввод!B15/2-Расчеты!B6),0)) | Q90: =IF(B90="Y",B90&C90,"")
J91: =IF(C91="BUY",Ввод!B13,Ввод!B14) | K91: =IF(C91="BUY",J91-E91,E91-J91) | L91: =IF(B91="Y",K91*D91*Ввод!B6+H91+I91,0) | M91: =IF(B91="Y",D91*Ввод!B6*J91/Ввод!B7,0) | N91: =IF(B91="Y",ROUND(MIN(D91*Ввод!B19,D91*0.5),2),0) | O91: =IF(B91<>"Y","НЕТ",IF(AND(Расчеты!B11="ДА",ABS(K91)>=Ввод!B18),"ЧАСТИЧНО ЗАКРЫТЬ","ДЕРЖАТЬ")) | P91: =IF(B91<>"Y",0,IFERROR((Ввод!B12-Расчеты!B3-Ввод!B15/2+Расчеты!B6)/(Расчеты!B4-Ввод!B12-Ввод!B15/2-Расчеты!B6),0)) | Q91: =IF(B91="Y",B91&C91,"")
J92: =IF(C92="BUY",Ввод!B13,Ввод!B14) | K92: =IF(C92="BUY",J92-E92,E92-J92) | L92: =IF(B92="Y",K92*D92*Ввод!B6+H92+I92,0) | M92: =IF(B92="Y",D92*Ввод!B6*J92/Ввод!B7,0) | N92: =IF(B92="Y",ROUND(MIN(D92*Ввод!B19,D92*0.5),2),0) | O92: =IF(B92<>"Y","НЕТ",IF(AND(Расчеты!B11="ДА",ABS(K92)>=Ввод!B18),"ЧАСТИЧНО ЗАКРЫТЬ","ДЕРЖАТЬ")) | P92: =IF(B92<>"Y",0,IFERROR((Ввод!B12-Расчеты!B3-Ввод!B15/2+Расчеты!B6)/(Расчеты!B4-Ввод!B12-Ввод!B15/2-Расчеты!B6),0)) | Q92: =IF(B92="Y",B92&C92,"")
J93: =IF(C93="BUY",Ввод!B13,Ввод!B14) | K93: =IF(C93="BUY",J93-E93,E93-J93) | L93: =IF(B93="Y",K93*D93*Ввод!B6+H93+I93,0) | M93: =IF(B93="Y",D93*Ввод!B6*J93/Ввод!B7,0) | N93: =IF(B93="Y",ROUND(MIN(D93*Ввод!B19,D93*0.5),2),0) | O93: =IF(B93<>"Y","НЕТ",IF(AND(Расчеты!B11="ДА",ABS(K93)>=Ввод!B18),"ЧАСТИЧНО ЗАКРЫТЬ","ДЕРЖАТЬ")) | P93: =IF(B93<>"Y",0,IFERROR((Ввод!B12-Расчеты!B3-Ввод!B15/2+Расчеты!B6)/(Расчеты!B4-Ввод!B12-Ввод!B15/2-Расчеты!B6),0)) | Q93: =IF(B93="Y",B93&C93,"")
J94: =IF(C94="BUY",Ввод!B13,Ввод!B14) | K94: =IF(C94="BUY",J94-E94,E94-J94) | L94: =IF(B94="Y",K94*D94*Ввод!B6+H94+I94,0) | M94: =IF(B94="Y",D94*Ввод!B6*J94/Ввод!B7,0) | N94: =IF(B94="Y",ROUND(MIN(D94*Ввод!B19,D94*0.5),2),0) | O94: =IF(B94<>"Y","НЕТ",IF(AND(Расчеты!B11="ДА",ABS(K94)>=Ввод!B18),"ЧАСТИЧНО ЗАКРЫТЬ","ДЕРЖАТЬ")) | P94: =IF(B94<>"Y",0,IFERROR((Ввод!B12-Расчеты!B3-Ввод!B15/2+Расчеты!B6)/(Расчеты!B4-Ввод!B12-Ввод!B15/2-Расчеты!B6),0)) | Q94: =IF(B94="Y",B94&C94,"")
J95: =IF(C95="BUY",Ввод!B13,Ввод!B14) | K95: =IF(C95="BUY",J95-E95,E95-J95) | L95: =IF(B95="Y",K95*D95*Ввод!B6+H95+I95,0) | M95: =IF(B95="Y",D95*Ввод!B6*J95/Ввод!B7,0) | N95: =IF(B95="Y",ROUND(MIN(D95*Ввод!B19,D95*0.5),2),0) | O95: =IF(B95<>"Y","НЕТ",IF(AND(Расчеты!B11="ДА",ABS(K95)>=Ввод!B18),"ЧАСТИЧНО ЗАКРЫТЬ","ДЕРЖАТЬ")) | P95: =IF(B95<>"Y",0,IFERROR((Ввод!B12-Расчеты!B3-Ввод!B15/2+Расчеты!B6)/(Расчеты!B4-Ввод!B12-Ввод!B15/2-Расчеты!B6),0)) | Q95: =IF(B95="Y",B95&C95,"")
J96: =IF(C96="BUY",Ввод!B13,Ввод!B14) | K96: =IF(C96="BUY",J96-E96,E96-J96) | L96: =IF(B96="Y",K96*D96*Ввод!B6+H96+I96,0) | M96: =IF(B96="Y",D96*Ввод!B6*J96/Ввод!B7,0) | N96: =IF(B96="Y",ROUND(MIN(D96*Ввод!B19,D96*0.5),2),0) | O96: =IF(B96<>"Y","НЕТ",IF(AND(Расчеты!B11="ДА",ABS(K96)>=Ввод!B18),"ЧАСТИЧНО ЗАКРЫТЬ","ДЕРЖАТЬ")) | P96: =IF(B96<>"Y",0,IFERROR((Ввод!B12-Расчеты!B3-Ввод!B15/2+Расчеты!B6)/(Расчеты!B4-Ввод!B12-Ввод!B15/2-Расчеты!B6),0)) | Q96: =IF(B96="Y",B96&C96,"")
J97: =IF(C97="BUY",Ввод!B13,Ввод!B14) | K97: =IF(C97="BUY",J97-E97,E97-J97) | L97: =IF(B97="Y",K97*D97*Ввод!B6+H97+I97,0) | M97: =IF(B97="Y",D97*Ввод!B6*J97/Ввод!B7,0) | N97: =IF(B97="Y",ROUND(MIN(D97*Ввод!B19,D97*0.5),2),0) | O97: =IF(B97<>"Y","НЕТ",IF(AND(Расчеты!B11="ДА",ABS(K97)>=Ввод!B18),"ЧАСТИЧНО ЗАКРЫТЬ","ДЕРЖАТЬ")) | P97: =IF(B97<>"Y",0,IFERROR((Ввод!B12-Расчеты!B3-Ввод!B15/2+Расчеты!B6)/(Расчеты!B4-Ввод!B12-Ввод!B15/2-Расчеты!B6),0)) | Q97: =IF(B97="Y",B97&C97,"")
J98: =IF(C98="BUY",Ввод!B13,Ввод!B14) | K98: =IF(C98="BUY",J98-E98,E98-J98) | L98: =IF(B98="Y",K98*D98*Ввод!B6+H98+I98,0) | M98: =IF(B98="Y",D98*Ввод!B6*J98/Ввод!B7,0) | N98: =IF(B98="Y",ROUND(MIN(D98*Ввод!B19,D98*0.5),2),0) | O98: =IF(B98<>"Y","НЕТ",IF(AND(Расчеты!B11="ДА",ABS(K98)>=Ввод!B18),"ЧАСТИЧНО ЗАКРЫТЬ","ДЕРЖАТЬ")) | P98: =IF(B98<>"Y",0,IFERROR((Ввод!B12-Расчеты!B3-Ввод!B15/2+Расчеты!B6)/(Расчеты!B4-Ввод!B12-Ввод!B15/2-Расчеты!B6),0)) | Q98: =IF(B98="Y",B98&C98,"")
J99: =IF(C99="BUY",Ввод!B13,Ввод!B14) | K99: =IF(C99="BUY",J99-E99,E99-J99) | L99: =IF(B99="Y",K99*D99*Ввод!B6+H99+I99,0) | M99: =IF(B99="Y",D99*Ввод!B6*J99/Ввод!B7,0) | N99: =IF(B99="Y",ROUND(MIN(D99*Ввод!B19,D99*0.5),2),0) | O99: =IF(B99<>"Y","НЕТ",IF(AND(Расчеты!B11="ДА",ABS(K99)>=Ввод!B18),"ЧАСТИЧНО ЗАКРЫТЬ","ДЕРЖАТЬ")) | P99: =IF(B99<>"Y",0,IFERROR((Ввод!B12-Расчеты!B3-Ввод!B15/2+Расчеты!B6)/(Расчеты!B4-Ввод!B12-Ввод!B15/2-Расчеты!B6),0)) | Q99: =IF(B99="Y",B99&C99,"")
J100: =IF(C100="BUY",Ввод!B13,Ввод!B14) | K100: =IF(C100="BUY",J100-E100,E100-J100) | L100: =IF(B100="Y",K100*D100*Ввод!B6+H100+I100,0) | M100: =IF(B100="Y",D100*Ввод!B6*J100/Ввод!B7,0) | N100: =IF(B100="Y",ROUND(MIN(D100*Ввод!B19,D100*0.5),2),0) | O100: =IF(B100<>"Y","НЕТ",IF(AND(Расчеты!B11="ДА",ABS(K100)>=Ввод!B18),"ЧАСТИЧНО ЗАКРЫТЬ","ДЕРЖАТЬ")) | P100: =IF(B100<>"Y",0,IFERROR((Ввод!B12-Расчеты!B3-Ввод!B15/2+Расчеты!B6)/(Расчеты!B4-Ввод!B12-Ввод!B15/2-Расчеты!B6),0)) | Q100: =IF(B100="Y",B100&C100,"")
...

Sheet Расчеты
A1: Сумма BUY лотов | B1: =SUMIFS(Позиции!D2:D201,Позиции!C2:C201,"BUY",Позиции!B2:B201,"Y")
A2: Сумма SELL лотов | B2: =SUMIFS(Позиции!D2:D201,Позиции!C2:C201,"SELL",Позиции!B2:B201,"Y")
A3: Средняя цена BUY | B3: =IF(B1=0,0,SUMPRODUCT((Позиции!C2:C201="BUY")*(Позиции!B2:B201="Y")*Позиции!D2:D201*Позиции!E2:E201)/B1)
A4: Средняя цена SELL | B4: =IF(B2=0,0,SUMPRODUCT((Позиции!C2:C201="SELL")*(Позиции!B2:B201="Y")*Позиции!D2:D201*Позиции!E2:E201)/B2)
A5: P_avg | B5: =IF(B1+B2=0,0,(B1*B3+B2*B4)/(B1+B2))
A6: δ = S + α*ATR | B6: =Ввод!B15 + Ввод!B17*Ввод!B16
A7: Левая часть survival: δ*Ls | B7: =B6*B2
A8: Правая часть survival: Δ*Lb | B8: =Ввод!B18*B1
A9: Условие survival | B9: =IF(B7>B8,"OK","FAIL")
A10: |P-P_avg| | B10: =ABS(Ввод!B12-B5)
A11: Триггер |P-P_avg|>Δ | B11: =IF(B10>Ввод!B18,"ДА","НЕТ")
A12: Общий плавающий P/L | B12: =SUM(Позиции!L2:L201)
A13: Общая маржа | B13: =SUM(Позиции!M2:M201)
A14: Нагрузка на депозит, % | B14: =IF(Ввод!B9=0,0,B13/Ввод!B9*100)
A15: Чистая экспозиция (BUY-SELL) | B15: =B1-B2
A16: Текущая просадка от баланса, % | B16: =IF(Ввод!B9=0,0,(B12/Ввод!B9)*100)
A17: ID первой активной BUY | B17: =IFERROR(INDEX(Позиции!A$2:A$201,MATCH("YBUY",Позиции!Q$2:Q$201,0)),"НЕТ")
A18: ID первой активной SELL | B18: =IFERROR(INDEX(Позиции!A$2:A$201,MATCH("YSELL",Позиции!Q$2:Q$201,0)),"НЕТ")
A19: Лот выбранной BUY | B19: =IFERROR(INDEX(Позиции!D$2:D$201,MATCH(B17,Позиции!A$2:A$201,0)),0)
A20: Лот выбранной SELL | B20: =IFERROR(INDEX(Позиции!D$2:D$201,MATCH(B18,Позиции!A$2:A$201,0)),0)

Sheet Следующий шаг
A1: Сценарий | B1: Целевая цена | C1: ID Позиции | D1: Для BUY/SELL | E1: Направление шага | F1: Рекоменд. лот | G1: Действие | H1: Частично закрыть лот | I1: Полностью закрыть? | J1: Причина
A2: Цена вверх на Δ | B2: =Ввод!B12+Ввод!B18 | C2: =IF(D2="BUY (Рекомендации для выбранной BUY)",Расчеты!B17,Расчеты!B18) | D2: BUY (Рекомендации для выбранной BUY) | E2: BUY trim / SELL hedge | F2: =IF(Расчеты!B17="НЕТ",0,MAX(0.01,ROUND(Расчеты!B19*Ввод!B19*Ввод!B23*0.5,2))) | G2: =IF(AND(Расчеты!B11="ДА",F2>0),"ЧАСТИЧНАЯ РЕБАЛАНСИРОВКА","ОЖИДАТЬ") | H2: =IF(F2=0,0,IF(OR(E2="BUY partial",E2="SELL partial"),ROUND(F2,2),ROUND(F2*0.6,2))) | I2: =IF(OR(Расчеты!B9="FAIL",Расчеты!B14>Ввод!B22,Расчеты!B16<-Ввод!B21),"ДА","НЕТ") | J2: =IF(I2="ДА","Риск превышен: survival/маржа/просадка","Нормальный цикл")
A3: Цена вверх на Δ | B3: =Ввод!B12+Ввод!B18 | C3: =IF(D3="BUY (Рекомендации для выбранной BUY)",Расчеты!B17,Расчеты!B18) | D3: SELL (Рекомендации для выбранной SELL) | E3: SELL partial | F3: =IF(Расчеты!B18="НЕТ",0,MAX(0.01,ROUND(Расчеты!B20*Ввод!B19*Ввод!B23*2,2))) | G3: =IF(AND(Расчеты!B11="ДА",F3>0),"ЧАСТИЧНАЯ РЕБАЛАНСИРОВКА","ОЖИДАТЬ") | H3: =IF(F3=0,0,IF(OR(E3="BUY partial",E3="SELL partial"),ROUND(F3,2),ROUND(F3*0.6,2))) | I3: =IF(OR(Расчеты!B9="FAIL",Расчеты!B14>Ввод!B22,Расчеты!B16<-Ввод!B21),"ДА","НЕТ") | J3: =IF(I3="ДА","Риск превышен: survival/маржа/просадка","Нормальный цикл")
A4: Цена вниз на Δ | B4: =Ввод!B12-Ввод!B18 | C4: =IF(D4="BUY (Рекомендации для выбранной BUY)",Расчеты!B17,Расчеты!B18) | D4: BUY (Рекомендации для выбранной BUY) | E4: BUY partial | F4: =IF(Расчеты!B17="НЕТ",0,MAX(0.01,ROUND(Расчеты!B19*Ввод!B19*Ввод!B23*2,2))) | G4: =IF(AND(Расчеты!B11="ДА",F4>0),"ЧАСТИЧНАЯ РЕБАЛАНСИРОВКА","ОЖИДАТЬ") | H4: =IF(F4=0,0,IF(OR(E4="BUY partial",E4="SELL partial"),ROUND(F4,2),ROUND(F4*0.6,2))) | I4: =IF(OR(Расчеты!B9="FAIL",Расчеты!B14>Ввод!B22,Расчеты!B16<-Ввод!B21),"ДА","НЕТ") | J4: =IF(I4="ДА","Риск превышен: survival/маржа/просадка","Нормальный цикл")
A5: Цена вниз на Δ | B5: =Ввод!B12-Ввод!B18 | C5: =IF(D5="BUY (Рекомендации для выбранной BUY)",Расчеты!B17,Расчеты!B18) | D5: SELL (Рекомендации для выбранной SELL) | E5: SELL trim / BUY hedge | F5: =IF(Расчеты!B18="НЕТ",0,MAX(0.01,ROUND(Расчеты!B20*Ввод!B19*Ввод!B23*0.5,2))) | G5: =IF(AND(Расчеты!B11="ДА",F5>0),"ЧАСТИЧНАЯ РЕБАЛАНСИРОВКА","ОЖИДАТЬ") | H5: =IF(F5=0,0,IF(OR(E5="BUY partial",E5="SELL partial"),ROUND(F5,2),ROUND(F5*0.6,2))) | I5: =IF(OR(Расчеты!B9="FAIL",Расчеты!B14>Ввод!B22,Расчеты!B16<-Ввод!B21),"ДА","НЕТ") | J5: =IF(I5="ДА","Риск превышен: survival/маржа/просадка","Нормальный цикл")
