Workbook
Name StartLot: 'ПАРАМЕТРЫ'!$B$2
Name Direction: 'ПАРАМЕТРЫ'!$B$3
Name MaxLevels: 'ПАРАМЕТРЫ'!$B$4
Name LotStep: 'ПАРАМЕТРЫ'!$B$5
Name UseRounding: 'ПАРАМЕТРЫ'!$B$6
Name BigPercent: 'ПАРАМЕТРЫ'!$B$7
Name SmallPercent: 'ПАРАМЕТРЫ'!$B$8
Name CloseFarPercent: 'ПАРАМЕТРЫ'!$B$9
Name CloseMode: 'ПАРАМЕТРЫ'!$B$10
Name ProfitReservePercent: 'ПАРАМЕТРЫ'!$B$11
Name MinReserveMoney: 'ПАРАМЕТРЫ'!$B$12
Name PointValuePerLot: 'ПАРАМЕТРЫ'!$B$13
Name Balance: 'ПАРАМЕТРЫ'!$B$14
Name Leverage: 'ПАРАМЕТРЫ'!$B$15
Name ContractSize: 'ПАРАМЕТРЫ'!$B$16
Name InstrumentPrice: 'ПАРАМЕТРЫ'!$B$17
Name MaxAdversePoints: 'ПАРАМЕТРЫ'!$B$18
Name StopOutPercent: 'ПАРАМЕТРЫ'!$B$19
Name MarginCallPercent: 'ПАРАМЕТРЫ'!$B$20

Sheet ПАРАМЕТРЫ
A1: Параметр | B1: Значение
A2: StartLot | B2: 1
A3: Direction | B3: DOWN
A4: MaxLevels | B4: 5
A5: LotStep | B5: 0.01
A6: UseRounding | B6: TRUE
A7: BigPercent | B7: 90
A8: SmallPercent | B8: 40
A9: CloseFarPercent | B9: 30
A10: CloseMode | B10: THEORETICAL
A11: ProfitReservePercent | B11: 30
A12: MinReserveMoney | B12: 5
A13: PointValuePerLot | B13: 10
A14: Balance | B14: 10000
A15: Leverage | B15: 100
A16: ContractSize | B16: 100000
A17: InstrumentPrice | B17: 1.1
A18: MaxAdversePoints | B18: 500
A19: StopOutPercent | B19: 50
A20: MarginCallPercent | B20: 100

Sheet Калькулятор
A1: Уровень | B1: Направление | C1: Ближний старт | D1: Дальний старт остаток | E1: Старт поз. самая дальняя | F1: Big % | G1: Big Lot Raw | H1: Big Lot Rounded | I1: Small % | J1: Small Lot Raw | K1: Small Lot Rounded | L1: Close Far % | M1: Max Close Far Lot | N1: Close By Profit Budget | O1: Actual Close Far Lot | P1: Close Mode | Q1: Новый ближний старт | R1: Новый дальний остаток | S1: Next Base Lot | T1: Сумма Big | U1: Сумма Small | V1: Сумма Close | W1: Статус | X1: Комментарий | Y1: Прибыль пакета до Close | Z1: Резерв деньги | AA1: Бюджет на Close | AB1: Убыток Far Start на 1 лот | AC1: Close Status | AD1: Total Big Lots | AE1: Total Small Lots | AF1: Total Open Lots | AG1: Net Lot | AH1: Margin Per Lot | AI1: Required Margin | AJ1: Margin Load % | AK1: Floating DD | AL1: Equity After DD | AM1: Free Margin | AN1: Margin Level % | AO1: Risk Status
A2: 1 | B2: =Direction | C2: =StartLot | D2: =StartLot | E2: =IF(Direction="DOWN","Start BUY","Start SELL") | F2: =BigPercent | G2: =C2*BigPercent/100 | H2: =IF(UseRounding="TRUE",ROUNDDOWN(G2/LotStep,0)*LotStep,G2) | I2: =SmallPercent | J2: =C2*SmallPercent/100 | K2: =IF(UseRounding="TRUE",ROUNDUP(J2/LotStep,0)*LotStep,J2) | L2: =CloseFarPercent | M2: =C2*CloseFarPercent/100 | N2: =IF(AA2<=0,0,ROUNDDOWN((AA2/AB2)/LotStep,0)*LotStep) | O2: =IF(CloseMode="THEORETICAL",MIN(M2,D2),MIN(M2,N2,D2)) | P2: =CloseMode | Q2: =C2-G2+J2 | R2: =D2-O2 | S2: =MIN(Q2,R2) | T2: =SUM($H$2:H2) | U2: =SUM($K$2:K2) | V2: =SUM($O$2:O2) | W2: =IF(OR(H2<LotStep,K2<LotStep,O2<LotStep,S2<LotStep,AJ2>100,AN2<StopOutPercent,R2<=0),"STOP","OK") | X2: =IF(Direction="DOWN","Уровень "&A2&". Цена идёт вниз. Ближний старт="&ROUND(C2,5)&". Открыть Big BUY "&ROUND(H2,5)&". Открыть Small SELL "&ROUND(K2,5)&". Частично закрыть дальний Start BUY "&ROUND(O2,5)&". Новый ближний старт="&ROUND(Q2,5)&". Остаток дальнего Start BUY="&ROUND(R2,5)&". Статус="&W2&".","Уровень "&A2&". Цена идёт вверх. Ближний старт="&ROUND(C2,5)&". Открыть Big SELL "&ROUND(H2,5)&". Открыть Small BUY "&ROUND(K2,5)&". Частично закрыть дальний Start SELL "&ROUND(O2,5)&". Новый ближний старт="&ROUND(Q2,5)&". Остаток дальнего Start SELL="&ROUND(R2,5)&". Статус="&W2&".") | Y2: =(H2+K2)*PointValuePerLot | Z2: =MAX(Y2*ProfitReservePercent/100,MinReserveMoney) | AA2: =Y2-Z2 | AB2: =MaxAdversePoints*PointValuePerLot | AC2: =IF(AND(CloseMode="SAFE_PROFIT_BUDGET",O2=0),"NO CLOSE","OK") | AD2: =T2 | AE2: =U2 | AF2: =AD2+AE2 | AG2: =ABS(AD2-AE2) | AH2: =ContractSize*InstrumentPrice/Leverage | AI2: =AF2*AH2 | AJ2: =AI2/Balance*100 | AK2: =AG2*MaxAdversePoints*PointValuePerLot | AL2: =Balance-AK2 | AM2: =AL2-AI2 | AN2: =IF(AI2=0,9999,AL2/AI2*100) | AO2: =IF(OR(AJ2>70,AN2<100),"CRITICAL",IF(OR(AJ2>50,AN2<150),"DANGER",IF(OR(AJ2>=30,AN2<=300),"WARNING","OK")))
A3: 2 | B3: =Direction | C3: =S2 | D3: =R2 | E3: =IF(Direction="DOWN","Start BUY","Start SELL") | F3: =BigPercent | G3: =C3*BigPercent/100 | H3: =IF(UseRounding="TRUE",ROUNDDOWN(G3/LotStep,0)*LotStep,G3) | I3: =SmallPercent | J3: =C3*SmallPercent/100 | K3: =IF(UseRounding="TRUE",ROUNDUP(J3/LotStep,0)*LotStep,J3) | L3: =CloseFarPercent | M3: =C3*CloseFarPercent/100 | N3: =IF(AA3<=0,0,ROUNDDOWN((AA3/AB3)/LotStep,0)*LotStep) | O3: =IF(CloseMode="THEORETICAL",MIN(M3,D3),MIN(M3,N3,D3)) | P3: =CloseMode | Q3: =C3-G3+J3 | R3: =D3-O3 | S3: =MIN(Q3,R3) | T3: =SUM($H$2:H3) | U3: =SUM($K$2:K3) | V3: =SUM($O$2:O3) | W3: =IF(OR(H3<LotStep,K3<LotStep,O3<LotStep,S3<LotStep,AJ3>100,AN3<StopOutPercent,R3<=0),"STOP","OK") | X3: =IF(Direction="DOWN","Уровень "&A3&". Цена идёт вниз. Ближний старт="&ROUND(C3,5)&". Открыть Big BUY "&ROUND(H3,5)&". Открыть Small SELL "&ROUND(K3,5)&". Частично закрыть дальний Start BUY "&ROUND(O3,5)&". Новый ближний старт="&ROUND(Q3,5)&". Остаток дальнего Start BUY="&ROUND(R3,5)&". Статус="&W3&".","Уровень "&A3&". Цена идёт вверх. Ближний старт="&ROUND(C3,5)&". Открыть Big SELL "&ROUND(H3,5)&". Открыть Small BUY "&ROUND(K3,5)&". Частично закрыть дальний Start SELL "&ROUND(O3,5)&". Новый ближний старт="&ROUND(Q3,5)&". Остаток дальнего Start SELL="&ROUND(R3,5)&". Статус="&W3&".") | Y3: =(H3+K3)*PointValuePerLot | Z3: =MAX(Y3*ProfitReservePercent/100,MinReserveMoney) | AA3: =Y3-Z3 | AB3: =MaxAdversePoints*PointValuePerLot | AC3: =IF(AND(CloseMode="SAFE_PROFIT_BUDGET",O3=0),"NO CLOSE","OK") | AD3: =T3 | AE3: =U3 | AF3: =AD3+AE3 | AG3: =ABS(AD3-AE3) | AH3: =ContractSize*InstrumentPrice/Leverage | AI3: =AF3*AH3 | AJ3: =AI3/Balance*100 | AK3: =AG3*MaxAdversePoints*PointValuePerLot | AL3: =Balance-AK3 | AM3: =AL3-AI3 | AN3: =IF(AI3=0,9999,AL3/AI3*100) | AO3: =IF(OR(AJ3>70,AN3<100),"CRITICAL",IF(OR(AJ3>50,AN3<150),"DANGER",IF(OR(AJ3>=30,AN3<=300),"WARNING","OK")))
A4: 3 | B4: =Direction | C4: =S3 | D4: =R3 | E4: =IF(Direction="DOWN","Start BUY","Start SELL") | F4: =BigPercent | G4: =C4*BigPercent/100 | H4: =IF(UseRounding="TRUE",ROUNDDOWN(G4/LotStep,0)*LotStep,G4) | I4: =SmallPercent | J4: =C4*SmallPercent/100 | K4: =IF(UseRounding="TRUE",ROUNDUP(J4/LotStep,0)*LotStep,J4) | L4: =CloseFarPercent | M4: =C4*CloseFarPercent/100 | N4: =IF(AA4<=0,0,ROUNDDOWN((AA4/AB4)/LotStep,0)*LotStep) | O4: =IF(CloseMode="THEORETICAL",MIN(M4,D4),MIN(M4,N4,D4)) | P4: =CloseMode | Q4: =C4-G4+J4 | R4: =D4-O4 | S4: =MIN(Q4,R4) | T4: =SUM($H$2:H4) | U4: =SUM($K$2:K4) | V4: =SUM($O$2:O4) | W4: =IF(OR(H4<LotStep,K4<LotStep,O4<LotStep,S4<LotStep,AJ4>100,AN4<StopOutPercent,R4<=0),"STOP","OK") | X4: =IF(Direction="DOWN","Уровень "&A4&". Цена идёт вниз. Ближний старт="&ROUND(C4,5)&". Открыть Big BUY "&ROUND(H4,5)&". Открыть Small SELL "&ROUND(K4,5)&". Частично закрыть дальний Start BUY "&ROUND(O4,5)&". Новый ближний старт="&ROUND(Q4,5)&". Остаток дальнего Start BUY="&ROUND(R4,5)&". Статус="&W4&".","Уровень "&A4&". Цена идёт вверх. Ближний старт="&ROUND(C4,5)&". Открыть Big SELL "&ROUND(H4,5)&". Открыть Small BUY "&ROUND(K4,5)&". Частично закрыть дальний Start SELL "&ROUND(O4,5)&". Новый ближний старт="&ROUND(Q4,5)&". Остаток дальнего Start SELL="&ROUND(R4,5)&". Статус="&W4&".") | Y4: =(H4+K4)*PointValuePerLot | Z4: =MAX(Y4*ProfitReservePercent/100,MinReserveMoney) | AA4: =Y4-Z4 | AB4: =MaxAdversePoints*PointValuePerLot | AC4: =IF(AND(CloseMode="SAFE_PROFIT_BUDGET",O4=0),"NO CLOSE","OK") | AD4: =T4 | AE4: =U4 | AF4: =AD4+AE4 | AG4: =ABS(AD4-AE4) | AH4: =ContractSize*InstrumentPrice/Leverage | AI4: =AF4*AH4 | AJ4: =AI4/Balance*100 | AK4: =AG4*MaxAdversePoints*PointValuePerLot | AL4: =Balance-AK4 | AM4: =AL4-AI4 | AN4: =IF(AI4=0,9999,AL4/AI4*100) | AO4: =IF(OR(AJ4>70,AN4<100),"CRITICAL",IF(OR(AJ4>50,AN4<150),"DANGER",IF(OR(AJ4>=30,AN4<=300),"WARNING","OK")))
A5: 4 | B5: =Direction | C5: =S4 | D5: =R4 | E5: =IF(Direction="DOWN","Start BUY","Start SELL") | F5: =BigPercent | G5: =C5*BigPercent/100 | H5: =IF(UseRounding="TRUE",ROUNDDOWN(G5/LotStep,0)*LotStep,G5) | I5: =SmallPercent | J5: =C5*SmallPercent/100 | K5: =IF(UseRounding="TRUE",ROUNDUP(J5/LotStep,0)*LotStep,J5) | L5: =CloseFarPercent | M5: =C5*CloseFarPercent/100 | N5: =IF(AA5<=0,0,ROUNDDOWN((AA5/AB5)/LotStep,0)*LotStep) | O5: =IF(CloseMode="THEORETICAL",MIN(M5,D5),MIN(M5,N5,D5)) | P5: =CloseMode | Q5: =C5-G5+J5 | R5: =D5-O5 | S5: =MIN(Q5,R5) | T5: =SUM($H$2:H5) | U5: =SUM($K$2:K5) | V5: =SUM($O$2:O5) | W5: =IF(OR(H5<LotStep,K5<LotStep,O5<LotStep,S5<LotStep,AJ5>100,AN5<StopOutPercent,R5<=0),"STOP","OK") | X5: =IF(Direction="DOWN","Уровень "&A5&". Цена идёт вниз. Ближний старт="&ROUND(C5,5)&". Открыть Big BUY "&ROUND(H5,5)&". Открыть Small SELL "&ROUND(K5,5)&". Частично закрыть дальний Start BUY "&ROUND(O5,5)&". Новый ближний старт="&ROUND(Q5,5)&". Остаток дальнего Start BUY="&ROUND(R5,5)&". Статус="&W5&".","Уровень "&A5&". Цена идёт вверх. Ближний старт="&ROUND(C5,5)&". Открыть Big SELL "&ROUND(H5,5)&". Открыть Small BUY "&ROUND(K5,5)&". Частично закрыть дальний Start SELL "&ROUND(O5,5)&". Новый ближний старт="&ROUND(Q5,5)&". Остаток дальнего Start SELL="&ROUND(R5,5)&". Статус="&W5&".") | Y5: =(H5+K5)*PointValuePerLot | Z5: =MAX(Y5*ProfitReservePercent/100,MinReserveMoney) | AA5: =Y5-Z5 | AB5: =MaxAdversePoints*PointValuePerLot | AC5: =IF(AND(CloseMode="SAFE_PROFIT_BUDGET",O5=0),"NO CLOSE","OK") | AD5: =T5 | AE5: =U5 | AF5: =AD5+AE5 | AG5: =ABS(AD5-AE5) | AH5: =ContractSize*InstrumentPrice/Leverage | AI5: =AF5*AH5 | AJ5: =AI5/Balance*100 | AK5: =AG5*MaxAdversePoints*PointValuePerLot | AL5: =Balance-AK5 | AM5: =AL5-AI5 | AN5: =IF(AI5=0,9999,AL5/AI5*100) | AO5: =IF(OR(AJ5>70,AN5<100),"CRITICAL",IF(OR(AJ5>50,AN5<150),"DANGER",IF(OR(AJ5>=30,AN5<=300),"WARNING","OK")))
A6: 5 | B6: =Direction | C6: =S5 | D6: =R5 | E6: =IF(Direction="DOWN","Start BUY","Start SELL") | F6: =BigPercent | G6: =C6*BigPercent/100 | H6: =IF(UseRounding="TRUE",ROUNDDOWN(G6/LotStep,0)*LotStep,G6) | I6: =SmallPercent | J6: =C6*SmallPercent/100 | K6: =IF(UseRounding="TRUE",ROUNDUP(J6/LotStep,0)*LotStep,J6) | L6: =CloseFarPercent | M6: =C6*CloseFarPercent/100 | N6: =IF(AA6<=0,0,ROUNDDOWN((AA6/AB6)/LotStep,0)*LotStep) | O6: =IF(CloseMode="THEORETICAL",MIN(M6,D6),MIN(M6,N6,D6)) | P6: =CloseMode | Q6: =C6-G6+J6 | R6: =D6-O6 | S6: =MIN(Q6,R6) | T6: =SUM($H$2:H6) | U6: =SUM($K$2:K6) | V6: =SUM($O$2:O6) | W6: =IF(OR(H6<LotStep,K6<LotStep,O6<LotStep,S6<LotStep,AJ6>100,AN6<StopOutPercent,R6<=0),"STOP","OK") | X6: =IF(Direction="DOWN","Уровень "&A6&". Цена идёт вниз. Ближний старт="&ROUND(C6,5)&". Открыть Big BUY "&ROUND(H6,5)&". Открыть Small SELL "&ROUND(K6,5)&". Частично закрыть дальний Start BUY "&ROUND(O6,5)&". Новый ближний старт="&ROUND(Q6,5)&". Остаток дальнего Start BUY="&ROUND(R6,5)&". Статус="&W6&".","Уровень "&A6&". Цена идёт вверх. Ближний старт="&ROUND(C6,5)&". Открыть Big SELL "&ROUND(H6,5)&". Открыть Small BUY "&ROUND(K6,5)&". Частично закрыть дальний Start SELL "&ROUND(O6,5)&". Новый ближний старт="&ROUND(Q6,5)&". Остаток дальнего Start SELL="&ROUND(R6,5)&". Статус="&W6&".") | Y6: =(H6+K6)*PointValuePerLot | Z6: =MAX(Y6*ProfitReservePercent/100,MinReserveMoney) | AA6: =Y6-Z6 | AB6: =MaxAdversePoints*PointValuePerLot | AC6: =IF(AND(CloseMode="SAFE_PROFIT_BUDGET",O6=0),"NO CLOSE","OK") | AD6: =T6 | AE6: =U6 | AF6: =AD6+AE6 | AG6: =ABS(AD6-AE6) | AH6: =ContractSize*InstrumentPrice/Leverage | AI6: =AF6*AH6 | AJ6: =AI6/Balance*100 | AK6: =AG6*MaxAdversePoints*PointValuePerLot | AL6: =Balance-AK6 | AM6: =AL6-AI6 | AN6: =IF(AI6=0,9999,AL6/AI6*100) | AO6: =IF(OR(AJ6>70,AN6<100),"CRITICAL",IF(OR(AJ6>50,AN6<150),"DANGER",IF(OR(AJ6>=30,AN6<=300),"WARNING","OK")))
A9: ИТОГИ САМОСЖИМАЮЩЕЙСЯ МОДЕЛИ
A10: StartLot | B10: =StartLot
A11: Direction | B11: =Direction
A12: Финальная сумма Big | B12: =T6
A13: Финальная сумма Small | B13: =U6
A14: Финальная сумма Close Far | B14: =V6
A15: Финальный ближний старт | B15: =Q6
A16: Финальный дальний остаток | B16: =R6
A17: Финальный NextBaseLot | B17: =S6
A18: Количество уровней OK | B18: =COUNTIF(W2:W6,"OK")
A19: Количество STOP | B19: =COUNTIF(W2:W6,"STOP")
A20: Финальный статус системы | B20: =IF(COUNTIF(W2:W6,"STOP")>0,"STOP","OK")

Sheet РИСК_АНАЛИЗ
A1: Уровень | B1: Total Big Lots | C1: Total Small Lots | D1: Total Open Lots | E1: Net Lot | F1: Margin Per Lot | G1: Required Margin | H1: Margin Load % | I1: Floating DD | J1: Equity After DD | K1: Free Margin | L1: Margin Level % | M1: Risk Status
A2: ='Калькулятор'!A2 | B2: ='Калькулятор'!AD2 | C2: ='Калькулятор'!AE2 | D2: ='Калькулятор'!AF2 | E2: ='Калькулятор'!AG2 | F2: ='Калькулятор'!AH2 | G2: ='Калькулятор'!AI2 | H2: ='Калькулятор'!AJ2 | I2: ='Калькулятор'!AK2 | ... M2: ='Калькулятор'!AO2
A3: ='Калькулятор'!A3 | B3: ='Калькулятор'!AD3 | C3: ='Калькулятор'!AE3 | D3: ='Калькулятор'!AF3 | E3: ='Калькулятор'!AG3 | F3: ='Калькулятор'!AH3 | G3: ='Калькулятор'!AI3 | H3: ='Калькулятор'!AJ3 | I3: ='Калькулятор'!AK3 | ... M3: ='Калькулятор'!AO3
A4: ='Калькулятор'!A4 | B4: ='Калькулятор'!AD4 | C4: ='Калькулятор'!AE4 | D4: ='Калькулятор'!AF4 | E4: ='Калькулятор'!AG4 | F4: ='Калькулятор'!AH4 | G4: ='Калькулятор'!AI4 | H4: ='Калькулятор'!AJ4 | I4: ='Калькулятор'!AK4 | ... M4: ='Калькулятор'!AO4
A5: ='Калькулятор'!A5 | B5: ='Калькулятор'!AD5 | C5: ='Калькулятор'!AE5 | D5: ='Калькулятор'!AF5 | E5: ='Калькулятор'!AG5 | F5: ='Калькулятор'!AH5 | G5: ='Калькулятор'!AI5 | H5: ='Калькулятор'!AJ5 | I5: ='Калькулятор'!AK5 | ... M5: ='Калькулятор'!AO5
A6: ='Калькулятор'!A6 | B6: ='Калькулятор'!AD6 | C6: ='Калькулятор'!AE6 | D6: ='Калькулятор'!AF6 | E6: ='Калькулятор'!AG6 | F6: ='Калькулятор'!AH6 | G6: ='Калькулятор'!AI6 | H6: ='Калькулятор'!AJ6 | I6: ='Калькулятор'!AK6 | ... M6: ='Калькулятор'!AO6

Sheet Тесты
A1: Проверка | B1: Формула | C1: Статус
A2: No #VALUE/#ЗНАЧ in comments | B2: =IF(COUNTIF(Калькулятор!X2:X6,"#VALUE!")+COUNTIF(Калькулятор!X2:X6,"#ЗНАЧ!")=0,"PASS","FAIL") | C2: =B2
A3: No #NAME/#ИМЯ | B3: =IF(COUNTIF(Калькулятор!A1:AO40,"#NAME?")+COUNTIF(Калькулятор!A1:AO40,"#ИМЯ?")+COUNTIF(РИСК_АНАЛИЗ!A1:M10,"#NAME?")+COUNTIF(РИСК_АНАЛИЗ!A1:M10,"#ИМЯ?")=0,"PASS","FAIL") | C3: =B3
A4: No #REF/#ССЫЛКА | B4: =IF(COUNTIF(Калькулятор!A1:AO40,"#REF!")+COUNTIF(Калькулятор!A1:AO40,"#ССЫЛКА!")+COUNTIF(РИСК_АНАЛИЗ!A1:M10,"#REF!")+COUNTIF(РИСК_АНАЛИЗ!A1:M10,"#ССЫЛКА!")=0,"PASS","FAIL") | C4: =B4
A5: No #DIV/0/#ДЕЛ/0 | B5: =IF(COUNTIF(Калькулятор!A1:AO40,"#DIV/0!")+COUNTIF(Калькулятор!A1:AO40,"#ДЕЛ/0!")+COUNTIF(РИСК_АНАЛИЗ!A1:M10,"#DIV/0!")+COUNTIF(РИСК_АНАЛИЗ!A1:M10,"#ДЕЛ/0!")=0,"PASS","FAIL") | C5: =B5
A6: L1 Actual Close formula | B6: =IF(OR(CloseMode<>"THEORETICAL",ABS(Калькулятор!O2-(Калькулятор!C2*CloseFarPercent/100))<1E-8),"PASS","FAIL") | C6: =B6
A7: L1 OpenLots=Big+Small | B7: =IF(ABS(Калькулятор!AF2-(Калькулятор!AD2+Калькулятор!AE2))<1E-8,"PASS","FAIL") | C7: =B7
A8: L1 Net=ABS(Big-Small) | B8: =IF(ABS(Калькулятор!AG2-ABS(Калькулятор!AD2-Калькулятор!AE2))<1E-8,"PASS","FAIL") | C8: =B8
A9: L1 RequiredMargin | B9: =IF(ABS(Калькулятор!AI2-(Калькулятор!AF2*Калькулятор!AH2))<1E-8,"PASS","FAIL") | C9: =B9
A10: L2 Actual Close formula | B10: =IF(OR(CloseMode<>"THEORETICAL",ABS(Калькулятор!O3-(Калькулятор!C3*CloseFarPercent/100))<1E-8),"PASS","FAIL") | C10: =B10
A11: L2 OpenLots=Big+Small | B11: =IF(ABS(Калькулятор!AF3-(Калькулятор!AD3+Калькулятор!AE3))<1E-8,"PASS","FAIL") | C11: =B11
A12: L2 Net=ABS(Big-Small) | B12: =IF(ABS(Калькулятор!AG3-ABS(Калькулятор!AD3-Калькулятор!AE3))<1E-8,"PASS","FAIL") | C12: =B12
A13: L2 RequiredMargin | B13: =IF(ABS(Калькулятор!AI3-(Калькулятор!AF3*Калькулятор!AH3))<1E-8,"PASS","FAIL") | C13: =B13
A14: L3 Actual Close formula | B14: =IF(OR(CloseMode<>"THEORETICAL",ABS(Калькулятор!O4-(Калькулятор!C4*CloseFarPercent/100))<1E-8),"PASS","FAIL") | C14: =B14
A15: L3 OpenLots=Big+Small | B15: =IF(ABS(Калькулятор!AF4-(Калькулятор!AD4+Калькулятор!AE4))<1E-8,"PASS","FAIL") | C15: =B15
A16: L3 Net=ABS(Big-Small) | B16: =IF(ABS(Калькулятор!AG4-ABS(Калькулятор!AD4-Калькулятор!AE4))<1E-8,"PASS","FAIL") | C16: =B16
A17: L3 RequiredMargin | B17: =IF(ABS(Калькулятор!AI4-(Калькулятор!AF4*Калькулятор!AH4))<1E-8,"PASS","FAIL") | C17: =B17
A18: L4 Actual Close formula | B18: =IF(OR(CloseMode<>"THEORETICAL",ABS(Калькулятор!O5-(Калькулятор!C5*CloseFarPercent/100))<1E-8),"PASS","FAIL") | C18: =B18
A19: L4 OpenLots=Big+Small | B19: =IF(ABS(Калькулятор!AF5-(Калькулятор!AD5+Калькулятор!AE5))<1E-8,"PASS","FAIL") | C19: =B19
A20: L4 Net=ABS(Big-Small) | B20: =IF(ABS(Калькулятор!AG5-ABS(Калькулятор!AD5-Калькулятор!AE5))<1E-8,"PASS","FAIL") | C20: =B20
A21: L4 RequiredMargin | B21: =IF(ABS(Калькулятор!AI5-(Калькулятор!AF5*Калькулятор!AH5))<1E-8,"PASS","FAIL") | C21: =B21
A22: L5 Actual Close formula | B22: =IF(OR(CloseMode<>"THEORETICAL",ABS(Калькулятор!O6-(Калькулятор!C6*CloseFarPercent/100))<1E-8),"PASS","FAIL") | C22: =B22
A23: L5 OpenLots=Big+Small | B23: =IF(ABS(Калькулятор!AF6-(Калькулятор!AD6+Калькулятор!AE6))<1E-8,"PASS","FAIL") | C23: =B23
A24: L5 Net=ABS(Big-Small) | B24: =IF(ABS(Калькулятор!AG6-ABS(Калькулятор!AD6-Калькулятор!AE6))<1E-8,"PASS","FAIL") | C24: =B24
A25: L5 RequiredMargin | B25: =IF(ABS(Калькулятор!AI6-(Калькулятор!AF6*Калькулятор!AH6))<1E-8,"PASS","FAIL") | C25: =B25
A26: StartLot=2 L1 close=0.6 or SKIP | B26: =IF(StartLot<>2,"SKIP",IF(AND(CloseMode="THEORETICAL",ABS(Калькулятор!O2-0.6)<1E-8),"PASS","FAIL")) | C26: =B26
A27: StartLot=2 L2 close=0.3 or SKIP | B27: =IF(StartLot<>2,"SKIP",IF(AND(CloseMode="THEORETICAL",ABS(Калькулятор!O3-0.3)<1E-8),"PASS","FAIL")) | C27: =B27
A28: StartLot=2 L3 close=0.15 or SKIP | B28: =IF(StartLot<>2,"SKIP",IF(AND(CloseMode="THEORETICAL",ABS(Калькулятор!O4-0.15)<1E-8),"PASS","FAIL")) | C28: =B28
A29: StartLot=2 L4 close=0.075 or SKIP | B29: =IF(StartLot<>2,"SKIP",IF(AND(CloseMode="THEORETICAL",ABS(Калькулятор!O5-0.075)<1E-8),"PASS","FAIL")) | C29: =B29
A30: StartLot=2 L5 close=0.0375 or SKIP | B30: =IF(StartLot<>2,"SKIP",IF(AND(CloseMode="THEORETICAL",ABS(Калькулятор!O6-0.0375)<1E-8),"PASS","FAIL")) | C30: =B30
A31: Comment contains Big BUY or Big SELL | B31: =IF(OR(ISNUMBER(SEARCH("Big BUY",Калькулятор!X2)),ISNUMBER(SEARCH("Big SELL",Калькулятор!X2))),"PASS","FAIL") | C31: =B31
A32: Comment not empty | B32: =IF(LEN(Калькулятор!X2)>20,"PASS","FAIL") | C32: =B32

Sheet Руководство
A1: См. MANUAL_RU.md

Sheet Описание
A1: SELF-COMPRESSING LOCK RECOVERY
