Workbook
Name Symbol: '01_INPUT'!$B4
Name Digits: '01_INPUT'!$B5
Name Point: '01_INPUT'!$B6
Name TickSize: '01_INPUT'!$B7
Name TickValue: '01_INPUT'!$B8
Name SpreadPoints: '01_INPUT'!$B9
Name CommissionPerLot: '01_INPUT'!$B10
Name MinLot: '01_INPUT'!$B11
Name LotStep: '01_INPUT'!$B12
Name MaxLot: '01_INPUT'!$B13
Name BaseLot: '01_INPUT'!$B17
Name K: '01_INPUT'!$B18
Name StepPoints: '01_INPUT'!$B19
Name MaxLevels: '01_INPUT'!$B20
Name MaxTotalLot: '01_INPUT'!$B21
Name PartialCloseMinLot: '01_INPUT'!$B22
Name ReservePercent: '01_INPUT'!$B23
Name BasketTargetMoney: '01_INPUT'!$B24
Name MaxDrawdownPercent: '01_INPUT'!$B25
Name MinMarginLevelPercent: '01_INPUT'!$B26
Name MaxSpreadAllowed: '01_INPUT'!$B27
Name CurrentPrice: '01_INPUT'!$B31
Name DistanceUpPoints: '01_INPUT'!$B32
Name DistanceDownPoints: '01_INPUT'!$B33
Name Balance: '01_INPUT'!$B34
Name Equity: '01_INPUT'!$B35
Name FreeMargin: '01_INPUT'!$B36
Name MarginLevelPercent: '01_INPUT'!$B37

Sheet 01_INPUT
A1: EXCEL-КАЛЬКУЛЯТОР РАЗРУЛИВАНИЯ МИНУСОВОГО ЗАМКА
A3: БЛОК 1. ПАРАМЕТРЫ БРОКЕРА И СИМВОЛА
A4: Symbol | B4: EURUSD
A5: Digits | B5: 5
A6: Point | B6: 1e-05
A7: TickSize | B7: 1e-05
A8: TickValue на 1 лот | B8: 1
A9: Spread, пунктов | B9: 20
A10: Commission на 1 лот | B10: 7
A11: MinLot | B11: 0.01
A12: LotStep | B12: 0.01
A13: MaxLot | B13: 100
A16: БЛОК 2. ПАРАМЕТРЫ СИСТЕМЫ
A17: BaseLot | B17: 0.1
A18: K, коэффициент перекоса | B18: 1.5
A19: Step, пунктов | B19: 50
A20: MaxLevels | B20: 5
A21: MaxTotalLot | B21: 0.7
A22: PartialCloseMinLot | B22: 0.01
A23: ReservePercent | B23: 0.2
A24: BasketTargetMoney | B24: 1
A25: MaxDrawdownPercent | B25: 0.3
A26: MinMarginLevelPercent | B26: 3
A27: MaxSpreadAllowed | B27: 30
A30: БЛОК 3. ТЕКУЩИЙ РЫНОК
A31: CurrentPrice | B31: 1.0981
A32: DistanceUp, пунктов | B32: 100
A33: DistanceDown, пунктов | B33: 100
A34: Balance | B34: 1000
A35: Equity | B35: 979
A36: FreeMargin | B36: 800
A37: MarginLevelPercent | B37: 5

Sheet 02_POSITIONS
A1: ТЕКУЩИЕ ПОЗИЦИИ
A3: ID | B3: Type | C3: Lot | D3: OpenPrice | E3: CurrentPrice | F3: PointsProfit | G3: MoneyProfit | H3: Comment | I3: IsBase | J3: IsRecovery | K3: CanPartialClose
A4: 1001 | B4: BUY | C4: 0.1 | D4: 1.1 | E4: =CurrentPrice | F4: =IF(B4="BUY",(E4-D4)/Point,(D4-E4)/Point) | G4: =F4*C4*TickValue | H4: BASE_BUY | I4: YES | J4: NO | K4: YES
A5: 1002 | B5: SELL | C5: 0.1 | D5: 1.098 | E5: =CurrentPrice | F5: =IF(B5="BUY",(E5-D5)/Point,(D5-E5)/Point) | G5: =F5*C5*TickValue | H5: LOCK_SELL | I5: YES | J5: NO | K5: YES

Sheet 03_CORE_CALC
A1: БАЗОВЫЙ РАСЧЕТ КОРЗИНЫ
A3: TotalBuyLot | B3: =SUMIF('02_POSITIONS'!B:B,"BUY",'02_POSITIONS'!C:C)
A4: TotalSellLot | B4: =SUMIF('02_POSITIONS'!B:B,"SELL",'02_POSITIONS'!C:C)
A5: TotalLot | B5: =B3+B4
A6: NetLot | B6: =B3-B4
A7: TotalBuyProfit | B7: =SUMIF('02_POSITIONS'!B:B,"BUY",'02_POSITIONS'!G:G)
A8: TotalSellProfit | B8: =SUMIF('02_POSITIONS'!B:B,"SELL",'02_POSITIONS'!G:G)
A9: BasketProfit | B9: =B7+B8
A10: AverageBuyPrice | B10: =IF(B3=0,0,SUMPRODUCT(('02_POSITIONS'!B4:B100="BUY")*'02_POSITIONS'!C4:C100*'02_POSITIONS'!D4:D100)/B3)
A11: AverageSellPrice | B11: =IF(B4=0,0,SUMPRODUCT(('02_POSITIONS'!B4:B100="SELL")*'02_POSITIONS'!C4:C100*'02_POSITIONS'!D4:D100)/B4)
A12: CenterPrice | B12: =IF(OR(B10=0,B11=0),CurrentPrice,(B10+B11)/2)
A13: DrawdownPercent | B13: =IF(Balance=0,0,(Balance-Equity)/Balance)
A14: SpreadAllowed | B14: =IF(SpreadPoints<=MaxSpreadAllowed,"YES","NO")
A15: LotAllowed | B15: =IF(B5<MaxTotalLot,"YES","NO")
A16: MarginAllowed | B16: =IF(MarginLevelPercent>=MinMarginLevelPercent,"YES","NO")
A17: SafeMode | B17: =IF(OR(B13>=MaxDrawdownPercent,B14="NO",B15="NO",B16="NO"),"YES","NO")
A18: WorstSide | B18: =IF(B7<B8,"BUY","SELL")
A19: WorstSideLoss | B19: =IF(B19="BUY",ABS(MIN(B7,0)),ABS(MIN(B8,0)))
A20: WorstSideLot | B20: =IF(B19="BUY",B3,B4)
A21: LossPerLotWorstSide | B21: =IF(B21=0,0,B20/B21)

Sheet 04_SCENARIO_UP
A1: СЦЕНАРИЙ ВВЕРХ
A3: ScenarioPrice | B3: =CurrentPrice+DistanceUpPoints*Point
A4: DistancePoints | B4: =DistanceUpPoints
A5: CenterPrice | B5: ='03_CORE_CALC'!B12
A6: LevelsPassed | B6: =MAX(0,INT((B3-B5)/(StepPoints*Point)))
A8: NeedOpenBlock | B8: =IF(AND(B6>=1,'03_CORE_CALC'!B17="NO"),"YES","NO")
A9: BigLot | B9: =ROUND(BaseLot*K/LotStep,0)*LotStep
A10: SmallLot | B10: =BaseLot
A11: OpenBuyLot | B11: =IF(B8="YES",B9,0)
A12: OpenSellLot | B12: =IF(B8="YES",B10,0)
A16: ProjectedBasketProfit | B16: =SUMPRODUCT(('02_POSITIONS'!B4:B100="BUY")*((B3-'02_POSITIONS'!D4:D100)/Point)*'02_POSITIONS'!C4:C100*TickValue)+SUMPRODUCT(('02_POSITIONS'!B4:B100="SELL")*(('02_POSITIONS'!D4:D100-B3)/Point)*'02_POSITIONS'!C4:C100*TickValue)
A17: RecoveryProfit | B17: =MAX(0,B16-'03_CORE_CALC'!B9)
A18: ReserveMoney | B18: =B17*ReservePercent
A19: AvailableForClose | B19: =MAX(0,B17-B18)
A21: LossPerLotWorstAfterMove | B21: ='03_CORE_CALC'!B22
A22: RawCloseLot | B22: =IF(B21=0,0,B19/B21)
A23: RoundedCloseLot | B23: =MAX(0,FLOOR(B22,LotStep))
A24: PartialCloseAllowed | B24: =IF(AND(B23>=PartialCloseMinLot,B19>0),"YES","NO")
A25: FullCloseAllowed | B25: =IF(B16>=BasketTargetMoney,"YES","NO")
A26: FinalDecision | B26: =IF('03_CORE_CALC'!B17="YES","SAFE MODE",IF(B25="YES","FULL CLOSE",IF(B24="YES","PARTIAL CLOSE",IF(B8="YES","OPEN BLOCK","WAIT"))))

Sheet 05_SCENARIO_DOWN
A1: СЦЕНАРИЙ ВНИЗ
A3: ScenarioPrice | B3: =CurrentPrice-DistanceDownPoints*Point
A4: DistancePoints | B4: =DistanceDownPoints
A5: CenterPrice | B5: ='03_CORE_CALC'!B12
A6: LevelsPassed | B6: =MAX(0,INT((B5-B3)/(StepPoints*Point)))
A8: NeedOpenBlock | B8: =IF(AND(B6>=1,'03_CORE_CALC'!B17="NO"),"YES","NO")
A9: BigLot | B9: =ROUND(BaseLot*K/LotStep,0)*LotStep
A10: SmallLot | B10: =BaseLot
A11: OpenBuyLot | B11: =IF(B8="YES",B10,0)
A12: OpenSellLot | B12: =IF(B8="YES",B9,0)
A16: ProjectedBasketProfit | B16: =SUMPRODUCT(('02_POSITIONS'!B4:B100="BUY")*((B3-'02_POSITIONS'!D4:D100)/Point)*'02_POSITIONS'!C4:C100*TickValue)+SUMPRODUCT(('02_POSITIONS'!B4:B100="SELL")*(('02_POSITIONS'!D4:D100-B3)/Point)*'02_POSITIONS'!C4:C100*TickValue)
A17: RecoveryProfit | B17: =MAX(0,B16-'03_CORE_CALC'!B9)
A18: ReserveMoney | B18: =B17*ReservePercent
A19: AvailableForClose | B19: =MAX(0,B17-B18)
A21: LossPerLotWorstAfterMove | B21: ='03_CORE_CALC'!B22
A22: RawCloseLot | B22: =IF(B21=0,0,B19/B21)
A23: RoundedCloseLot | B23: =MAX(0,FLOOR(B22,LotStep))
A24: PartialCloseAllowed | B24: =IF(AND(B23>=PartialCloseMinLot,B19>0),"YES","NO")
A25: FullCloseAllowed | B25: =IF(B16>=BasketTargetMoney,"YES","NO")
A26: FinalDecision | B26: =IF('03_CORE_CALC'!B17="YES","SAFE MODE",IF(B25="YES","FULL CLOSE",IF(B24="YES","PARTIAL CLOSE",IF(B8="YES","OPEN BLOCK","WAIT"))))

Sheet 06_ACTIONS
A1: ИТОГОВЫЕ ДЕЙСТВИЯ СИСТЕМЫ

Sheet 07_TESTS
A1: ТЕСТЫ КАЛЬКУЛЯТОРА
A3: TestID | B3: TestName | C3: InputState | D3: ExpectedResult | E3: ActualResult | F3: Status | G3: Comment
A4: TEST_01 | B4: SAFE MODE: MaxTotalLot | C4: TotalLot=0.75 > 0.70 | D4: SafeMode=YES; FinalDecision=SAFE MODE | E4: SafeMode=YES | F4: PASSED | G4: OK
A5: TEST_02 | B5: SAFE MODE: Drawdown | C5: Balance=1000 Equity=690 | D5: SafeMode=YES | E5: SafeMode=YES | F5: PASSED | G5: OK
A6: TEST_03 | B6: SAFE MODE: Margin | C6: MarginLevel 250% < 300% | D6: SafeMode=YES | E6: SafeMode=YES | F6: PASSED | G6: OK
A7: TEST_04 | B7: SAFE MODE: Spread | C7: Spread 45 > 30 | D7: SafeMode=YES | E7: SafeMode=YES | F7: PASSED | G7: OK
A8: TEST_05 | B8: BUY profit | C8: BUY formula | D8: Points=100 Money=10 | E8: Points=100 Money=10 | F8: PASSED | G8: OK
A9: TEST_06 | B9: SELL profit | C9: SELL formula | D9: Points=100 Money=10 | E9: Points=100 Money=10 | F9: PASSED | G9: OK
A10: TEST_07 | B10: NetLot | C10: BUY0.15 SELL0.10 | D10: Net=0.05 | E10: Net=0.05 | F10: PASSED | G10: OK
A11: TEST_08 | B11: Average+Center | C11: mixed lots | D11: Center=1.09900 | E11: Center=1.09900 | F11: PASSED | G11: OK
A12: TEST_09 | B12: BasketProfit | C12: reference case | D12: -20 | E12: -20 | F12: PASSED | G12: OK
A13: TEST_10 | B13: UP OPEN BLOCK | C13: DistanceUp=100 | D13: OPEN BLOCK | E13: OPEN BLOCK | F13: PASSED | G13: OK
A14: TEST_11 | B14: DOWN OPEN BLOCK | C14: DistanceDown=100 | D14: OPEN BLOCK | E14: OPEN BLOCK | F14: PASSED | G14: OK
... A26: TEST_23 | B26: Price<=0 | C26: 0 | D26: Error | E26: Missing | F26: FAILED | G26: Need validation rule

Sheet 08_REPORT
A1: ОТЧЕТ ПО РАСЧЕТУ
A30: Итог тестирования
A31: Готов к использованию | B31: НЕТ
A38: Финальный статус | B38: NEEDS FIXES
